{"@t":"2021-01-14T17:02:28.7347789Z","@mt":"{LogPrefix} Terminating {Immediate}","LogPrefix":"[TempFileCleanup] ","Immediate":"","SourceContext":"Umbraco.Web.Scheduling.BackgroundTaskRunner","ProcessId":60708,"ProcessName":"iisexpress","ThreadId":264,"AppDomainId":3,"AppDomainAppId":"LMW3SVC2ROOT","MachineName":"CJ","Log4NetLevel":"INFO "}
{"@t":"2021-01-14T17:02:28.7347789Z","@mt":"{LogPrefix} Terminating {Immediate}","LogPrefix":"[RebuildIndexesOnStartup] ","Immediate":"","SourceContext":"Umbraco.Web.Scheduling.BackgroundTaskRunner","ProcessId":60708,"ProcessName":"iisexpress","ThreadId":264,"AppDomainId":3,"AppDomainAppId":"LMW3SVC2ROOT","MachineName":"CJ","Log4NetLevel":"INFO "}
{"@t":"2021-01-14T17:02:28.7367746Z","@mt":"{LogPrefix} Canceling tasks","LogPrefix":"[TempFileCleanup] ","SourceContext":"Umbraco.Web.Scheduling.BackgroundTaskRunner","ProcessId":60708,"ProcessName":"iisexpress","ThreadId":144,"AppDomainId":3,"AppDomainAppId":"LMW3SVC2ROOT","MachineName":"CJ","Log4NetLevel":"INFO "}
{"@t":"2021-01-14T17:02:28.7367746Z","@mt":"{LogPrefix} Canceling tasks","LogPrefix":"[RebuildIndexesOnStartup] ","SourceContext":"Umbraco.Web.Scheduling.BackgroundTaskRunner","ProcessId":60708,"ProcessName":"iisexpress","ThreadId":101,"AppDomainId":3,"AppDomainAppId":"LMW3SVC2ROOT","MachineName":"CJ","Log4NetLevel":"INFO "}
{"@t":"2021-01-14T17:02:28.7377720Z","@mt":"{LogPrefix} Tasks {TaskStatus}, terminated","LogPrefix":"[TempFileCleanup] ","TaskStatus":"cancelled","SourceContext":"Umbraco.Web.Scheduling.BackgroundTaskRunner","ProcessId":60708,"ProcessName":"iisexpress","ThreadId":144,"AppDomainId":3,"AppDomainAppId":"LMW3SVC2ROOT","MachineName":"CJ","Log4NetLevel":"INFO "}
{"@t":"2021-01-14T17:02:28.7377720Z","@mt":"{LogPrefix} Tasks {TaskStatus}, terminated","LogPrefix":"[RebuildIndexesOnStartup] ","TaskStatus":"cancelled","SourceContext":"Umbraco.Web.Scheduling.BackgroundTaskRunner","ProcessId":60708,"ProcessName":"iisexpress","ThreadId":101,"AppDomainId":3,"AppDomainAppId":"LMW3SVC2ROOT","MachineName":"CJ","Log4NetLevel":"INFO "}
{"@t":"2021-01-14T17:02:28.7417607Z","@mt":"{LogPrefix} Terminating {Immediate}","LogPrefix":"[LogScrubber] ","Immediate":"","SourceContext":"Umbraco.Web.Scheduling.BackgroundTaskRunner","ProcessId":60708,"ProcessName":"iisexpress","ThreadId":264,"AppDomainId":3,"AppDomainAppId":"LMW3SVC2ROOT","MachineName":"CJ","Log4NetLevel":"INFO "}
{"@t":"2021-01-14T17:02:28.7417607Z","@mt":"{LogPrefix} Terminating {Immediate}","LogPrefix":"[KeepAlive] ","Immediate":"","SourceContext":"Umbraco.Web.Scheduling.BackgroundTaskRunner","ProcessId":60708,"ProcessName":"iisexpress","ThreadId":264,"AppDomainId":3,"AppDomainAppId":"LMW3SVC2ROOT","MachineName":"CJ","Log4NetLevel":"INFO "}
{"@t":"2021-01-14T17:02:28.7417607Z","@mt":"{LogPrefix} Terminating {Immediate}","LogPrefix":"[ScheduledPublishing] ","Immediate":"","SourceContext":"Umbraco.Web.Scheduling.BackgroundTaskRunner","ProcessId":60708,"ProcessName":"iisexpress","ThreadId":264,"AppDomainId":3,"AppDomainAppId":"LMW3SVC2ROOT","MachineName":"CJ","Log4NetLevel":"INFO "}
{"@t":"2021-01-14T17:02:28.7417607Z","@mt":"{LogPrefix} Terminating {Immediate}","LogPrefix":"[ServerInstProcess] ","Immediate":"","SourceContext":"Umbraco.Web.Scheduling.BackgroundTaskRunner","ProcessId":60708,"ProcessName":"iisexpress","ThreadId":264,"AppDomainId":3,"AppDomainAppId":"LMW3SVC2ROOT","MachineName":"CJ","Log4NetLevel":"INFO "}
{"@t":"2021-01-14T17:02:28.7417607Z","@mt":"{LogPrefix} Canceling tasks","LogPrefix":"[ScheduledPublishing] ","SourceContext":"Umbraco.Web.Scheduling.BackgroundTaskRunner","ProcessId":60708,"ProcessName":"iisexpress","ThreadId":21,"AppDomainId":3,"AppDomainAppId":"LMW3SVC2ROOT","MachineName":"CJ","Log4NetLevel":"INFO "}
{"@t":"2021-01-14T17:02:28.7417607Z","@mt":"{LogPrefix} Canceling tasks","LogPrefix":"[KeepAlive] ","SourceContext":"Umbraco.Web.Scheduling.BackgroundTaskRunner","ProcessId":60708,"ProcessName":"iisexpress","ThreadId":181,"AppDomainId":3,"AppDomainAppId":"LMW3SVC2ROOT","MachineName":"CJ","Log4NetLevel":"INFO "}
{"@t":"2021-01-14T17:02:28.7417607Z","@mt":"{LogPrefix} Tasks {TaskStatus}, terminated","LogPrefix":"[ScheduledPublishing] ","TaskStatus":"cancelled","SourceContext":"Umbraco.Web.Scheduling.BackgroundTaskRunner","ProcessId":60708,"ProcessName":"iisexpress","ThreadId":21,"AppDomainId":3,"AppDomainAppId":"LMW3SVC2ROOT","MachineName":"CJ","Log4NetLevel":"INFO "}
{"@t":"2021-01-14T17:02:28.7417607Z","@mt":"{LogPrefix} Canceling tasks","LogPrefix":"[ServerInstProcess] ","SourceContext":"Umbraco.Web.Scheduling.BackgroundTaskRunner","ProcessId":60708,"ProcessName":"iisexpress","ThreadId":164,"AppDomainId":3,"AppDomainAppId":"LMW3SVC2ROOT","MachineName":"CJ","Log4NetLevel":"INFO "}
{"@t":"2021-01-14T17:02:28.7417607Z","@mt":"{LogPrefix} Tasks {TaskStatus}, terminated","LogPrefix":"[ServerInstProcess] ","TaskStatus":"cancelled","SourceContext":"Umbraco.Web.Scheduling.BackgroundTaskRunner","ProcessId":60708,"ProcessName":"iisexpress","ThreadId":164,"AppDomainId":3,"AppDomainAppId":"LMW3SVC2ROOT","MachineName":"CJ","Log4NetLevel":"INFO "}
{"@t":"2021-01-14T17:02:28.7417607Z","@mt":"{LogPrefix} Tasks {TaskStatus}, terminated","LogPrefix":"[KeepAlive] ","TaskStatus":"cancelled","SourceContext":"Umbraco.Web.Scheduling.BackgroundTaskRunner","ProcessId":60708,"ProcessName":"iisexpress","ThreadId":181,"AppDomainId":3,"AppDomainAppId":"LMW3SVC2ROOT","MachineName":"CJ","Log4NetLevel":"INFO "}
{"@t":"2021-01-14T17:02:28.7417607Z","@mt":"{LogPrefix} Terminating {Immediate}","LogPrefix":"[ServerRegistration] ","Immediate":"","SourceContext":"Umbraco.Web.Scheduling.BackgroundTaskRunner","ProcessId":60708,"ProcessName":"iisexpress","ThreadId":264,"AppDomainId":3,"AppDomainAppId":"LMW3SVC2ROOT","MachineName":"CJ","Log4NetLevel":"INFO "}
{"@t":"2021-01-14T17:02:28.7417607Z","@mt":"{LogPrefix} Terminating {Immediate}","LogPrefix":"[Umbraco.Web.Scheduling.IBackgroundTask] ","Immediate":"","SourceContext":"Umbraco.Web.Scheduling.BackgroundTaskRunner","ProcessId":60708,"ProcessName":"iisexpress","ThreadId":264,"AppDomainId":3,"AppDomainAppId":"LMW3SVC2ROOT","MachineName":"CJ","Log4NetLevel":"INFO "}
{"@t":"2021-01-14T17:02:28.7417607Z","@mt":"{LogPrefix} Terminating {Immediate}","LogPrefix":"[ScheduledTasks] ","Immediate":"","SourceContext":"Umbraco.Web.Scheduling.BackgroundTaskRunner","ProcessId":60708,"ProcessName":"iisexpress","ThreadId":264,"AppDomainId":3,"AppDomainAppId":"LMW3SVC2ROOT","MachineName":"CJ","Log4NetLevel":"INFO "}
{"@t":"2021-01-14T17:02:28.7417607Z","@mt":"{LogPrefix} Canceling tasks","LogPrefix":"[ServerRegistration] ","SourceContext":"Umbraco.Web.Scheduling.BackgroundTaskRunner","ProcessId":60708,"ProcessName":"iisexpress","ThreadId":87,"AppDomainId":3,"AppDomainAppId":"LMW3SVC2ROOT","MachineName":"CJ","Log4NetLevel":"INFO "}
{"@t":"2021-01-14T17:02:28.7417607Z","@mt":"{LogPrefix} Tasks {TaskStatus}, terminated","LogPrefix":"[ServerRegistration] ","TaskStatus":"cancelled","SourceContext":"Umbraco.Web.Scheduling.BackgroundTaskRunner","ProcessId":60708,"ProcessName":"iisexpress","ThreadId":87,"AppDomainId":3,"AppDomainAppId":"LMW3SVC2ROOT","MachineName":"CJ","Log4NetLevel":"INFO "}
{"@t":"2021-01-14T17:02:28.7417607Z","@mt":"{LogPrefix} Canceling tasks","LogPrefix":"[ScheduledTasks] ","SourceContext":"Umbraco.Web.Scheduling.BackgroundTaskRunner","ProcessId":60708,"ProcessName":"iisexpress","ThreadId":193,"AppDomainId":3,"AppDomainAppId":"LMW3SVC2ROOT","MachineName":"CJ","Log4NetLevel":"INFO "}
{"@t":"2021-01-14T17:02:28.7427593Z","@mt":"{LogPrefix} Canceling tasks","LogPrefix":"[Umbraco.Web.Scheduling.IBackgroundTask] ","SourceContext":"Umbraco.Web.Scheduling.BackgroundTaskRunner","ProcessId":60708,"ProcessName":"iisexpress","ThreadId":233,"AppDomainId":3,"AppDomainAppId":"LMW3SVC2ROOT","MachineName":"CJ","Log4NetLevel":"INFO "}
{"@t":"2021-01-14T17:02:28.7427593Z","@mt":"{LogPrefix} Tasks {TaskStatus}, terminated","LogPrefix":"[ScheduledTasks] ","TaskStatus":"cancelled","SourceContext":"Umbraco.Web.Scheduling.BackgroundTaskRunner","ProcessId":60708,"ProcessName":"iisexpress","ThreadId":193,"AppDomainId":3,"AppDomainAppId":"LMW3SVC2ROOT","MachineName":"CJ","Log4NetLevel":"INFO "}
{"@t":"2021-01-14T17:02:28.7427593Z","@mt":"{LogPrefix} Tasks {TaskStatus}, terminated","LogPrefix":"[Umbraco.Web.Scheduling.IBackgroundTask] ","TaskStatus":"cancelled","SourceContext":"Umbraco.Web.Scheduling.BackgroundTaskRunner","ProcessId":60708,"ProcessName":"iisexpress","ThreadId":233,"AppDomainId":3,"AppDomainAppId":"LMW3SVC2ROOT","MachineName":"CJ","Log4NetLevel":"INFO "}
{"@t":"2021-01-14T17:02:28.7417607Z","@mt":"{LogPrefix} Canceling tasks","LogPrefix":"[LogScrubber] ","SourceContext":"Umbraco.Web.Scheduling.BackgroundTaskRunner","ProcessId":60708,"ProcessName":"iisexpress","ThreadId":272,"AppDomainId":3,"AppDomainAppId":"LMW3SVC2ROOT","MachineName":"CJ","Log4NetLevel":"INFO "}
{"@t":"2021-01-14T17:02:28.7427593Z","@mt":"{LogPrefix} Tasks {TaskStatus}, terminated","LogPrefix":"[LogScrubber] ","TaskStatus":"cancelled","SourceContext":"Umbraco.Web.Scheduling.BackgroundTaskRunner","ProcessId":60708,"ProcessName":"iisexpress","ThreadId":272,"AppDomainId":3,"AppDomainAppId":"LMW3SVC2ROOT","MachineName":"CJ","Log4NetLevel":"INFO "}
{"@t":"2021-01-14T17:02:28.7427593Z","@mt":"{LogPrefix} Terminating {Immediate}","LogPrefix":"[HealthCheckNotifier] ","Immediate":"","SourceContext":"Umbraco.Web.Scheduling.BackgroundTaskRunner","ProcessId":60708,"ProcessName":"iisexpress","ThreadId":264,"AppDomainId":3,"AppDomainAppId":"LMW3SVC2ROOT","MachineName":"CJ","Log4NetLevel":"INFO "}
{"@t":"2021-01-14T17:02:28.7427593Z","@mt":"{LogPrefix} Canceling tasks","LogPrefix":"[HealthCheckNotifier] ","SourceContext":"Umbraco.Web.Scheduling.BackgroundTaskRunner","ProcessId":60708,"ProcessName":"iisexpress","ThreadId":117,"AppDomainId":3,"AppDomainAppId":"LMW3SVC2ROOT","MachineName":"CJ","Log4NetLevel":"INFO "}
{"@t":"2021-01-14T17:02:28.7427593Z","@mt":"{LogPrefix} Tasks {TaskStatus}, terminated","LogPrefix":"[HealthCheckNotifier] ","TaskStatus":"cancelled","SourceContext":"Umbraco.Web.Scheduling.BackgroundTaskRunner","ProcessId":60708,"ProcessName":"iisexpress","ThreadId":117,"AppDomainId":3,"AppDomainAppId":"LMW3SVC2ROOT","MachineName":"CJ","Log4NetLevel":"INFO "}
{"@t":"2021-01-14T17:02:28.7467524Z","@mt":"Stopping ({SignalSource})","SignalSource":"environment","SourceContext":"Umbraco.Core.Runtime.MainDom","ProcessId":60708,"ProcessName":"iisexpress","ThreadId":264,"AppDomainId":3,"AppDomainAppId":"LMW3SVC2ROOT","MachineName":"CJ","Log4NetLevel":"INFO "}
{"@t":"2021-01-14T17:02:28.7856437Z","@mt":"Released from MainDom","SourceContext":"Umbraco.Web.PublishedCache.NuCache.PublishedSnapshotService","ProcessId":60708,"ProcessName":"iisexpress","ThreadId":264,"AppDomainId":3,"AppDomainAppId":"LMW3SVC2ROOT","MachineName":"CJ","Log4NetLevel":"INFO "}
{"@t":"2021-01-14T17:02:28.7866418Z","@mt":"{StartMessage} [Timing {TimingId}]","StartMessage":"Examine shutting down","TimingId":"c825e48","SourceContext":"Umbraco.Web.Search.ExamineComponent","ProcessId":60708,"ProcessName":"iisexpress","ThreadId":264,"AppDomainId":3,"AppDomainAppId":"LMW3SVC2ROOT","MachineName":"CJ","Log4NetLevel":"INFO "}
{"@t":"2021-01-14T17:02:28.7896340Z","@mt":"{EndMessage} ({Duration}ms) [Timing {TimingId}]","EndMessage":"Completed.","Duration":3,"TimingId":"c825e48","SourceContext":"Umbraco.Web.Search.ExamineComponent","ProcessId":60708,"ProcessName":"iisexpress","ThreadId":264,"AppDomainId":3,"AppDomainAppId":"LMW3SVC2ROOT","MachineName":"CJ","Log4NetLevel":"INFO "}
{"@t":"2021-01-14T17:02:28.7896340Z","@mt":"Released ({SignalSource})","SignalSource":"environment","SourceContext":"Umbraco.Core.Runtime.MainDom","ProcessId":60708,"ProcessName":"iisexpress","ThreadId":264,"AppDomainId":3,"AppDomainAppId":"LMW3SVC2ROOT","MachineName":"CJ","Log4NetLevel":"INFO "}
{"@t":"2021-01-14T17:02:28.7906320Z","@mt":"{LogPrefix} Terminating {Immediate}","LogPrefix":"[TelemetryReporter] ","Immediate":"","SourceContext":"Umbraco.Web.Scheduling.BackgroundTaskRunner","ProcessId":60708,"ProcessName":"iisexpress","ThreadId":264,"AppDomainId":3,"AppDomainAppId":"LMW3SVC2ROOT","MachineName":"CJ","Log4NetLevel":"INFO "}
{"@t":"2021-01-14T17:02:29.7540550Z","@mt":"{LogPrefix} Canceling tasks","LogPrefix":"[TelemetryReporter] ","SourceContext":"Umbraco.Web.Scheduling.BackgroundTaskRunner","ProcessId":60708,"ProcessName":"iisexpress","ThreadId":17,"AppDomainId":3,"AppDomainAppId":"LMW3SVC2ROOT","MachineName":"CJ","Log4NetLevel":"INFO "}
{"@t":"2021-01-14T17:02:29.7540550Z","@mt":"{LogPrefix} Tasks {TaskStatus}, terminated","LogPrefix":"[TelemetryReporter] ","TaskStatus":"cancelled","SourceContext":"Umbraco.Web.Scheduling.BackgroundTaskRunner","ProcessId":60708,"ProcessName":"iisexpress","ThreadId":17,"AppDomainId":3,"AppDomainAppId":"LMW3SVC2ROOT","MachineName":"CJ","Log4NetLevel":"INFO "}
{"@t":"2021-01-14T17:02:29.8099058Z","@mt":"Application shutdown. Details: {ShutdownReason}\r\n\r\n_shutDownMessage={ShutdownMessage}\r\n\r\n_shutDownStack={ShutdownStack}","ShutdownReason":"ConfigurationChange","ShutdownMessage":"Change in App_Offline.htm\r\nHostingEnvironment initiated shutdown\r\nChange in App_Offline.htm\r\nChange in App_Offline.htm\r\nHostingEnvironment caused shutdown","ShutdownStack":"   at System.Environment.GetStackTrace(Exception e, Boolean needFileInfo)\r\n   at System.Environment.get_StackTrace()\r\n   at System.Web.Hosting.HostingEnvironment.InitiateShutdownInternal()\r\n   at System.Web.Hosting.HostingEnvironment.InitiateShutdownWithoutDemand()\r\n   at System.Web.HttpRuntime.ShutdownAppDomain(String stackTrace)\r\n   at System.Web.HttpRuntime.OnAppOfflineFileChange(Object sender, FileChangeEvent e)\r\n   at System.Web.DirectoryMonitor.FireNotifications()\r\n   at System.Web.Util.WorkItem.CallCallbackWithAssert(WorkItemCallback callback)\r\n   at System.Web.Util.WorkItem.OnQueueUserWorkItemCompletion(Object state)\r\n   at System.Threading.QueueUserWorkItemCallback.WaitCallback_Context(Object state)\r\n   at System.Threading.ExecutionContext.RunInternal(ExecutionContext executionContext, ContextCallback callback, Object state, Boolean preserveSyncCtx)\r\n   at System.Threading.ExecutionContext.Run(ExecutionContext executionContext, ContextCallback callback, Object state, Boolean preserveSyncCtx)\r\n   at System.Threading.QueueUserWorkItemCallback.System.Threading.IThreadPoolWorkItem.ExecuteWorkItem()\r\n   at System.Threading.ThreadPoolWorkQueue.Dispatch()\r\n   at System.Threading._ThreadPoolWaitCallback.PerformWaitCallback()","SourceContext":"Umbraco.Web.UmbracoApplicationBase","ProcessId":60708,"ProcessName":"iisexpress","ThreadId":264,"AppDomainId":3,"AppDomainAppId":"LMW3SVC2ROOT","MachineName":"CJ","Log4NetLevel":"INFO "}
{"@t":"2021-01-14T17:18:33.4031541Z","@mt":"{StartMessage} [Timing {TimingId}]","StartMessage":"Booting Umbraco 8.10.1.","TimingId":"0d3e1fc","SourceContext":"Umbraco.Core.Runtime.CoreRuntime","ProcessId":48900,"ProcessName":"iisexpress","ThreadId":1,"AppDomainId":2,"AppDomainAppId":"LMW3SVC2ROOT","MachineName":"CJ","Log4NetLevel":"INFO ","HttpRequestNumber":1,"HttpRequestId":"41f62f89-9584-4a94-ba8f-7d45397d029d"}
{"@t":"2021-01-14T17:18:33.4300472Z","@mt":"Booting site '{HostingSiteName}', app '{HostingApplicationID}', path '{HostingPhysicalPath}', server '{MachineName}'.","HostingSiteName":"Umbraco","HostingApplicationID":"/LM/W3SVC/2/ROOT","HostingPhysicalPath":"D:\\Project\\Great One Platform\\Umbraco\\Umbraco\\","MachineName":"CJ","SourceContext":"Umbraco.Core.Runtime.CoreRuntime","ProcessId":48900,"ProcessName":"iisexpress","ThreadId":1,"AppDomainId":2,"AppDomainAppId":"LMW3SVC2ROOT","Log4NetLevel":"INFO ","HttpRequestNumber":1,"HttpRequestId":"41f62f89-9584-4a94-ba8f-7d45397d029d"}
{"@t":"2021-01-14T17:18:33.5068792Z","@mt":"Acquiring.","SourceContext":"Umbraco.Core.Runtime.MainDom","ProcessId":48900,"ProcessName":"iisexpress","ThreadId":1,"AppDomainId":2,"AppDomainAppId":"LMW3SVC2ROOT","MachineName":"CJ","Log4NetLevel":"INFO ","HttpRequestNumber":1,"HttpRequestId":"41f62f89-9584-4a94-ba8f-7d45397d029d"}
{"@t":"2021-01-14T17:18:33.5088714Z","@mt":"Acquired.","SourceContext":"Umbraco.Core.Runtime.MainDom","ProcessId":48900,"ProcessName":"iisexpress","ThreadId":1,"AppDomainId":2,"AppDomainAppId":"LMW3SVC2ROOT","MachineName":"CJ","Log4NetLevel":"INFO ","HttpRequestNumber":1,"HttpRequestId":"41f62f89-9584-4a94-ba8f-7d45397d029d"}
{"@t":"2021-01-14T17:18:34.0624620Z","@mt":"{StartMessage} [Timing {TimingId}]","StartMessage":"Resolving composer types.","TimingId":"388e204","SourceContext":"Umbraco.Core.Runtime.CoreRuntime","ProcessId":48900,"ProcessName":"iisexpress","ThreadId":1,"AppDomainId":2,"AppDomainAppId":"LMW3SVC2ROOT","MachineName":"CJ","Log4NetLevel":"INFO ","HttpRequestNumber":1,"HttpRequestId":"41f62f89-9584-4a94-ba8f-7d45397d029d"}
{"@t":"2021-01-14T17:18:34.1960718Z","@mt":"{EndMessage} ({Duration}ms) [Timing {TimingId}]","EndMessage":"Resolved.","Duration":132,"TimingId":"388e204","SourceContext":"Umbraco.Core.Runtime.CoreRuntime","ProcessId":48900,"ProcessName":"iisexpress","ThreadId":1,"AppDomainId":2,"AppDomainAppId":"LMW3SVC2ROOT","MachineName":"CJ","Log4NetLevel":"INFO ","HttpRequestNumber":1,"HttpRequestId":"41f62f89-9584-4a94-ba8f-7d45397d029d"}
{"@t":"2021-01-14T17:18:34.3187448Z","@mt":"ModelsBuilder.Embedded is disabled, the external ModelsBuilder was detected.","SourceContext":"Umbraco.ModelsBuilder.Embedded.Compose.ModelsBuilderComposer","ProcessId":48900,"ProcessName":"iisexpress","ThreadId":1,"AppDomainId":2,"AppDomainAppId":"LMW3SVC2ROOT","MachineName":"CJ","Log4NetLevel":"INFO ","HttpRequestNumber":1,"HttpRequestId":"41f62f89-9584-4a94-ba8f-7d45397d029d"}
{"@t":"2021-01-14T17:18:34.7286516Z","@mt":"Registered with MainDom, localContentDbExists? {LocalContentDbExists}, localMediaDbExists? {LocalMediaDbExists}","LocalContentDbExists":true,"LocalMediaDbExists":true,"SourceContext":"Umbraco.Web.PublishedCache.NuCache.PublishedSnapshotService","ProcessId":48900,"ProcessName":"iisexpress","ThreadId":1,"AppDomainId":2,"AppDomainAppId":"LMW3SVC2ROOT","MachineName":"CJ","Log4NetLevel":"INFO ","HttpRequestNumber":1,"HttpRequestId":"41f62f89-9584-4a94-ba8f-7d45397d029d"}
{"@t":"2021-01-14T17:18:34.7286516Z","@mt":"Creating the content store, localContentDbExists? {LocalContentDbExists}","LocalContentDbExists":true,"SourceContext":"Umbraco.Web.PublishedCache.NuCache.PublishedSnapshotService","ProcessId":48900,"ProcessName":"iisexpress","ThreadId":1,"AppDomainId":2,"AppDomainAppId":"LMW3SVC2ROOT","MachineName":"CJ","Log4NetLevel":"INFO ","HttpRequestNumber":1,"HttpRequestId":"41f62f89-9584-4a94-ba8f-7d45397d029d"}
{"@t":"2021-01-14T17:18:34.7296466Z","@mt":"Creating the media store, localMediaDbExists? {LocalMediaDbExists}","LocalMediaDbExists":true,"SourceContext":"Umbraco.Web.PublishedCache.NuCache.PublishedSnapshotService","ProcessId":48900,"ProcessName":"iisexpress","ThreadId":1,"AppDomainId":2,"AppDomainAppId":"LMW3SVC2ROOT","MachineName":"CJ","Log4NetLevel":"INFO ","HttpRequestNumber":1,"HttpRequestId":"41f62f89-9584-4a94-ba8f-7d45397d029d"}
{"@t":"2021-01-14T17:18:35.0428097Z","@mt":"Could not find an editor with alias {EditorAlias}, treating as Label. The site may fail to boot and / or load data types and run.","@l":"Warning","EditorAlias":"UmbracoForms.FormPicker","SourceContext":"Umbraco.Core.Models.DataType","ProcessId":48900,"ProcessName":"iisexpress","ThreadId":1,"AppDomainId":2,"AppDomainAppId":"LMW3SVC2ROOT","MachineName":"CJ","Log4NetLevel":"WARN ","HttpRequestNumber":1,"HttpRequestId":"41f62f89-9584-4a94-ba8f-7d45397d029d"}
{"@t":"2021-01-14T17:18:35.0508209Z","@mt":"{StartMessage} [Timing {TimingId}]","StartMessage":"Loading content from local cache file","TimingId":"e733a14","SourceContext":"Umbraco.Web.PublishedCache.NuCache.PublishedSnapshotService","ProcessId":48900,"ProcessName":"iisexpress","ThreadId":1,"AppDomainId":2,"AppDomainAppId":"LMW3SVC2ROOT","MachineName":"CJ","Log4NetLevel":"INFO ","HttpRequestNumber":1,"HttpRequestId":"41f62f89-9584-4a94-ba8f-7d45397d029d"}
{"@t":"2021-01-14T17:18:35.0747569Z","@mt":"{EndMessage} ({Duration}ms) [Timing {TimingId}]","EndMessage":"Completed.","Duration":23,"TimingId":"e733a14","SourceContext":"Umbraco.Web.PublishedCache.NuCache.PublishedSnapshotService","ProcessId":48900,"ProcessName":"iisexpress","ThreadId":1,"AppDomainId":2,"AppDomainAppId":"LMW3SVC2ROOT","MachineName":"CJ","Log4NetLevel":"INFO ","HttpRequestNumber":1,"HttpRequestId":"41f62f89-9584-4a94-ba8f-7d45397d029d"}
{"@t":"2021-01-14T17:18:35.1146503Z","@mt":"{StartMessage} [Timing {TimingId}]","StartMessage":"Loading media from local cache file","TimingId":"df3a348","SourceContext":"Umbraco.Web.PublishedCache.NuCache.PublishedSnapshotService","ProcessId":48900,"ProcessName":"iisexpress","ThreadId":1,"AppDomainId":2,"AppDomainAppId":"LMW3SVC2ROOT","MachineName":"CJ","Log4NetLevel":"INFO ","HttpRequestNumber":1,"HttpRequestId":"41f62f89-9584-4a94-ba8f-7d45397d029d"}
{"@t":"2021-01-14T17:18:35.1156157Z","@mt":"{EndMessage} ({Duration}ms) [Timing {TimingId}]","EndMessage":"Completed.","Duration":0,"TimingId":"df3a348","SourceContext":"Umbraco.Web.PublishedCache.NuCache.PublishedSnapshotService","ProcessId":48900,"ProcessName":"iisexpress","ThreadId":1,"AppDomainId":2,"AppDomainAppId":"LMW3SVC2ROOT","MachineName":"CJ","Log4NetLevel":"INFO ","HttpRequestNumber":1,"HttpRequestId":"41f62f89-9584-4a94-ba8f-7d45397d029d"}
{"@t":"2021-01-14T17:18:35.1993903Z","@mt":"Profiler is VoidProfiler, not profiling (must run debug mode to profile).","SourceContext":"Umbraco.Web.Logging.WebProfilerComponent","ProcessId":48900,"ProcessName":"iisexpress","ThreadId":1,"AppDomainId":2,"AppDomainAppId":"LMW3SVC2ROOT","MachineName":"CJ","Log4NetLevel":"INFO ","HttpRequestNumber":1,"HttpRequestId":"41f62f89-9584-4a94-ba8f-7d45397d029d"}
{"@t":"2021-01-14T17:18:35.3021475Z","@mt":"Initializing Umbraco internal event handlers for cache refreshing.","SourceContext":"Umbraco.Web.Cache.DistributedCacheBinderComponent","ProcessId":48900,"ProcessName":"iisexpress","ThreadId":1,"AppDomainId":2,"AppDomainAppId":"LMW3SVC2ROOT","MachineName":"CJ","Log4NetLevel":"INFO ","HttpRequestNumber":1,"HttpRequestId":"41f62f89-9584-4a94-ba8f-7d45397d029d"}
{"@t":"2021-01-14T17:18:35.3549746Z","@mt":"Adding examine event handlers for {RegisteredIndexers} index providers.","RegisteredIndexers":3,"SourceContext":"Umbraco.Web.Search.ExamineComponent","ProcessId":48900,"ProcessName":"iisexpress","ThreadId":1,"AppDomainId":2,"AppDomainAppId":"LMW3SVC2ROOT","MachineName":"CJ","Log4NetLevel":"INFO ","HttpRequestNumber":1,"HttpRequestId":"41f62f89-9584-4a94-ba8f-7d45397d029d"}
{"@t":"2021-01-14T17:18:35.4208319Z","@mt":"No last synced Id found, this generally means this is a new server/install. The server will build its caches and indexes, and then adjust its last synced Id to the latest found in the database and maintain cache updates based on that Id.","@l":"Warning","SourceContext":"Umbraco.Core.Sync.DatabaseServerMessenger","ProcessId":48900,"ProcessName":"iisexpress","ThreadId":1,"AppDomainId":2,"AppDomainAppId":"LMW3SVC2ROOT","MachineName":"CJ","Log4NetLevel":"WARN ","HttpRequestNumber":1,"HttpRequestId":"41f62f89-9584-4a94-ba8f-7d45397d029d"}
{"@t":"2021-01-14T17:18:35.4308061Z","@mt":"{StartMessage} [Timing {TimingId}]","StartMessage":"Loading content from database","TimingId":"4f65750","SourceContext":"Umbraco.Web.PublishedCache.NuCache.PublishedSnapshotService","ProcessId":48900,"ProcessName":"iisexpress","ThreadId":1,"AppDomainId":2,"AppDomainAppId":"LMW3SVC2ROOT","MachineName":"CJ","Log4NetLevel":"INFO ","HttpRequestNumber":1,"HttpRequestId":"41f62f89-9584-4a94-ba8f-7d45397d029d"}
{"@t":"2021-01-14T17:18:35.7804702Z","@mt":"{EndMessage} ({Duration}ms) [Timing {TimingId}]","EndMessage":"Completed.","Duration":349,"TimingId":"4f65750","SourceContext":"Umbraco.Web.PublishedCache.NuCache.PublishedSnapshotService","ProcessId":48900,"ProcessName":"iisexpress","ThreadId":1,"AppDomainId":2,"AppDomainAppId":"LMW3SVC2ROOT","MachineName":"CJ","Log4NetLevel":"INFO ","HttpRequestNumber":1,"HttpRequestId":"41f62f89-9584-4a94-ba8f-7d45397d029d"}
{"@t":"2021-01-14T17:18:35.7834633Z","@mt":"{StartMessage} [Timing {TimingId}]","StartMessage":"Loading media from database","TimingId":"2d54741","SourceContext":"Umbraco.Web.PublishedCache.NuCache.PublishedSnapshotService","ProcessId":48900,"ProcessName":"iisexpress","ThreadId":1,"AppDomainId":2,"AppDomainAppId":"LMW3SVC2ROOT","MachineName":"CJ","Log4NetLevel":"INFO ","HttpRequestNumber":1,"HttpRequestId":"41f62f89-9584-4a94-ba8f-7d45397d029d"}
{"@t":"2021-01-14T17:18:35.9811097Z","@mt":"{EndMessage} ({Duration}ms) [Timing {TimingId}]","EndMessage":"Completed.","Duration":197,"TimingId":"2d54741","SourceContext":"Umbraco.Web.PublishedCache.NuCache.PublishedSnapshotService","ProcessId":48900,"ProcessName":"iisexpress","ThreadId":1,"AppDomainId":2,"AppDomainAppId":"LMW3SVC2ROOT","MachineName":"CJ","Log4NetLevel":"INFO ","HttpRequestNumber":1,"HttpRequestId":"41f62f89-9584-4a94-ba8f-7d45397d029d"}
{"@t":"2021-01-14T17:18:35.9821066Z","@mt":"Starting initialize async background thread.","SourceContext":"Umbraco.Web.Search.BackgroundIndexRebuilder","ProcessId":48900,"ProcessName":"iisexpress","ThreadId":1,"AppDomainId":2,"AppDomainAppId":"LMW3SVC2ROOT","MachineName":"CJ","Log4NetLevel":"INFO ","HttpRequestNumber":1,"HttpRequestId":"41f62f89-9584-4a94-ba8f-7d45397d029d"}
{"@t":"2021-01-14T17:18:36.0529362Z","@mt":"Forcing index {IndexerName} to be unlocked since it was left in a locked state","IndexerName":"InternalIndex","SourceContext":"Umbraco.Examine.ExamineExtensions","ProcessId":48900,"ProcessName":"iisexpress","ThreadId":1,"AppDomainId":2,"AppDomainAppId":"LMW3SVC2ROOT","MachineName":"CJ","Log4NetLevel":"INFO ","HttpRequestNumber":1,"HttpRequestId":"41f62f89-9584-4a94-ba8f-7d45397d029d"}
{"@t":"2021-01-14T17:18:36.0529362Z","@mt":"Forcing index {IndexerName} to be unlocked since it was left in a locked state","IndexerName":"MembersIndex","SourceContext":"Umbraco.Examine.ExamineExtensions","ProcessId":48900,"ProcessName":"iisexpress","ThreadId":1,"AppDomainId":2,"AppDomainAppId":"LMW3SVC2ROOT","MachineName":"CJ","Log4NetLevel":"INFO ","HttpRequestNumber":1,"HttpRequestId":"41f62f89-9584-4a94-ba8f-7d45397d029d"}
{"@t":"2021-01-14T17:18:36.0529362Z","@mt":"Forcing index {IndexerName} to be unlocked since it was left in a locked state","IndexerName":"ExternalIndex","SourceContext":"Umbraco.Examine.ExamineExtensions","ProcessId":48900,"ProcessName":"iisexpress","ThreadId":1,"AppDomainId":2,"AppDomainAppId":"LMW3SVC2ROOT","MachineName":"CJ","Log4NetLevel":"INFO ","HttpRequestNumber":1,"HttpRequestId":"41f62f89-9584-4a94-ba8f-7d45397d029d"}
{"@t":"2021-01-14T17:18:36.0529362Z","@mt":"Call was made to RebuildIndexes but the task runner for rebuilding is already running","@l":"Warning","SourceContext":"Umbraco.Web.Search.BackgroundIndexRebuilder","ProcessId":48900,"ProcessName":"iisexpress","ThreadId":1,"AppDomainId":2,"AppDomainAppId":"LMW3SVC2ROOT","MachineName":"CJ","Log4NetLevel":"WARN ","HttpRequestNumber":1,"HttpRequestId":"41f62f89-9584-4a94-ba8f-7d45397d029d"}
{"@t":"2021-01-14T17:18:36.0529362Z","@mt":"{EndMessage} ({Duration}ms) [Timing {TimingId}]","EndMessage":"Booted.","Duration":2657,"TimingId":"0d3e1fc","SourceContext":"Umbraco.Core.Runtime.CoreRuntime","ProcessId":48900,"ProcessName":"iisexpress","ThreadId":1,"AppDomainId":2,"AppDomainAppId":"LMW3SVC2ROOT","MachineName":"CJ","Log4NetLevel":"INFO ","HttpRequestNumber":1,"HttpRequestId":"41f62f89-9584-4a94-ba8f-7d45397d029d"}
{"@t":"2021-01-14T17:18:36.3928027Z","@mt":"New url {Url} detected, re-discovering application url.","Url":"http://localhost:58464/umbraco","SourceContext":"Umbraco.Core.Sync.ApplicationUrlHelper","ProcessId":48900,"ProcessName":"iisexpress","ThreadId":9,"AppDomainId":2,"AppDomainAppId":"LMW3SVC2ROOT","MachineName":"CJ","Log4NetLevel":"INFO ","HttpRequestNumber":2,"HttpRequestId":"0e894607-8f2b-4671-bf11-cdff1db6443a"}
{"@t":"2021-01-14T17:18:36.3937675Z","@mt":"ApplicationUrl: {UmbracoAppUrl} (UmbracoModule request)","UmbracoAppUrl":"http://localhost:58464/umbraco","SourceContext":"Umbraco.Core.Sync.ApplicationUrlHelper","ProcessId":48900,"ProcessName":"iisexpress","ThreadId":9,"AppDomainId":2,"AppDomainAppId":"LMW3SVC2ROOT","MachineName":"CJ","Log4NetLevel":"INFO ","HttpRequestNumber":2,"HttpRequestId":"0e894607-8f2b-4671-bf11-cdff1db6443a"}
{"@t":"2021-01-14T17:20:11.2506432Z","@mt":"[{EventType}] Event Id: {EventId}, State: {State}","EventType":"Information","EventId":0,"State":"Login attempt succeeded for username admin@admin.com from IP address ::1","SourceContext":"Umbraco.Core.Logging.OwinLogger","ProcessId":48900,"ProcessName":"iisexpress","ThreadId":14,"AppDomainId":2,"AppDomainAppId":"LMW3SVC2ROOT","MachineName":"CJ","Log4NetLevel":"INFO ","HttpRequestNumber":3,"HttpRequestId":"0a155c0c-40a9-49f8-826d-cc85bf37ce39"}
{"@t":"2021-01-14T17:20:11.2516674Z","@mt":"[{EventType}] Event Id: {EventId}, State: {State}","EventType":"Information","EventId":0,"State":"User: admin@admin.com logged in from IP address ::1","SourceContext":"Umbraco.Core.Logging.OwinLogger","ProcessId":48900,"ProcessName":"iisexpress","ThreadId":14,"AppDomainId":2,"AppDomainAppId":"LMW3SVC2ROOT","MachineName":"CJ","Log4NetLevel":"INFO ","HttpRequestNumber":3,"HttpRequestId":"0a155c0c-40a9-49f8-826d-cc85bf37ce39"}
{"@t":"2021-01-14T17:20:11.7960856Z","@mt":"Could not validate XSRF token","@l":"Error","@x":"System.Web.Mvc.HttpAntiForgeryException (0x80004005): The provided anti-forgery token was meant for a different claims-based user than the current user.\r\n   at System.Web.Helpers.AntiXsrf.TokenValidator.ValidateTokens(HttpContextBase httpContext, IIdentity identity, AntiForgeryToken sessionToken, AntiForgeryToken fieldToken)\r\n   at System.Web.Helpers.AntiXsrf.AntiForgeryWorker.Validate(HttpContextBase httpContext, String cookieToken, String formToken)\r\n   at System.Web.Helpers.AntiForgery.Validate(String cookieToken, String formToken)\r\n   at Umbraco.Web.WebApi.Filters.AngularAntiForgeryHelper.ValidateTokens(String cookieToken, String headerToken) in D:\\a\\1\\s\\src\\Umbraco.Web\\WebApi\\Filters\\AngularAntiForgeryHelper.cs:line 58","SourceContext":"Umbraco.Web.WebApi.Filters.AngularAntiForgeryHelper","ProcessId":48900,"ProcessName":"iisexpress","ThreadId":14,"AppDomainId":2,"AppDomainAppId":"LMW3SVC2ROOT","MachineName":"CJ","Log4NetLevel":"ERROR","HttpRequestNumber":3,"HttpRequestId":"0a155c0c-40a9-49f8-826d-cc85bf37ce39"}
{"@t":"2021-01-14T17:20:32.2193219Z","@mt":"Document {ContentName} (id={ContentId}) has been unpublished.","ContentName":"Home","ContentId":1104,"SourceContext":"Umbraco.Core.Services.Implement.ContentService","ProcessId":48900,"ProcessName":"iisexpress","ThreadId":9,"AppDomainId":2,"AppDomainAppId":"LMW3SVC2ROOT","MachineName":"CJ","Log4NetLevel":"INFO ","HttpRequestNumber":4,"HttpRequestId":"ba0264c0-ede6-4e4c-975a-3df338e5a5f4"}
{"@t":"2021-01-14T17:20:36.2358504Z","@mt":"Document {ContentName} (id={ContentId}) has been published.","ContentName":"HomePage","ContentId":1148,"SourceContext":"Umbraco.Core.Services.Implement.ContentService","ProcessId":48900,"ProcessName":"iisexpress","ThreadId":42,"AppDomainId":2,"AppDomainAppId":"LMW3SVC2ROOT","MachineName":"CJ","Log4NetLevel":"INFO ","HttpRequestNumber":5,"HttpRequestId":"52f9edc2-8768-4085-be4d-41577ae5e188"}
{"@t":"2021-01-14T17:21:28.9243040Z","@mt":"{StartMessage} [Timing {TimingId}]","StartMessage":"Loading content from database","TimingId":"d231def","SourceContext":"Umbraco.Web.PublishedCache.NuCache.PublishedSnapshotService","ProcessId":48900,"ProcessName":"iisexpress","ThreadId":45,"AppDomainId":2,"AppDomainAppId":"LMW3SVC2ROOT","MachineName":"CJ","Log4NetLevel":"INFO ","HttpRequestNumber":6,"HttpRequestId":"2336cc7b-25cb-4b9a-8e70-a43f560b9e10"}
{"@t":"2021-01-14T17:21:29.0928196Z","@mt":"{EndMessage} ({Duration}ms) [Timing {TimingId}]","EndMessage":"Completed.","Duration":169,"TimingId":"d231def","SourceContext":"Umbraco.Web.PublishedCache.NuCache.PublishedSnapshotService","ProcessId":48900,"ProcessName":"iisexpress","ThreadId":45,"AppDomainId":2,"AppDomainAppId":"LMW3SVC2ROOT","MachineName":"CJ","Log4NetLevel":"INFO ","HttpRequestNumber":6,"HttpRequestId":"2336cc7b-25cb-4b9a-8e70-a43f560b9e10"}
{"@t":"2021-01-14T17:21:29.1247343Z","@mt":"{StartMessage} [Timing {TimingId}]","StartMessage":"Loading media from database","TimingId":"fa20f8f","SourceContext":"Umbraco.Web.PublishedCache.NuCache.PublishedSnapshotService","ProcessId":48900,"ProcessName":"iisexpress","ThreadId":45,"AppDomainId":2,"AppDomainAppId":"LMW3SVC2ROOT","MachineName":"CJ","Log4NetLevel":"INFO ","HttpRequestNumber":6,"HttpRequestId":"2336cc7b-25cb-4b9a-8e70-a43f560b9e10"}
{"@t":"2021-01-14T17:21:29.2546324Z","@mt":"{EndMessage} ({Duration}ms) [Timing {TimingId}]","EndMessage":"Completed.","Duration":129,"TimingId":"fa20f8f","SourceContext":"Umbraco.Web.PublishedCache.NuCache.PublishedSnapshotService","ProcessId":48900,"ProcessName":"iisexpress","ThreadId":45,"AppDomainId":2,"AppDomainAppId":"LMW3SVC2ROOT","MachineName":"CJ","Log4NetLevel":"INFO ","HttpRequestNumber":6,"HttpRequestId":"2336cc7b-25cb-4b9a-8e70-a43f560b9e10"}
{"@t":"2021-01-14T17:21:43.1072486Z","@mt":"Scheduled health check results:","SourceContext":"Umbraco.Web.HealthCheck.HealthCheckResults","ProcessId":48900,"ProcessName":"iisexpress","ThreadId":32,"AppDomainId":2,"AppDomainAppId":"LMW3SVC2ROOT","MachineName":"CJ","Log4NetLevel":"INFO "}
{"@t":"2021-01-14T17:21:43.1072486Z","@mt":"Checks for '{HealthCheckName}' all completed successfully.","HealthCheckName":"Folder & File Permissions","SourceContext":"Umbraco.Web.HealthCheck.HealthCheckResults","ProcessId":48900,"ProcessName":"iisexpress","ThreadId":32,"AppDomainId":2,"AppDomainAppId":"LMW3SVC2ROOT","MachineName":"CJ","Log4NetLevel":"INFO "}
{"@t":"2021-01-14T17:21:43.1072486Z","@mt":"Result for {HealthCheckName}: {HealthCheckResult}, Message: '{HealthCheckMessage}'","HealthCheckName":"Folder & File Permissions","HealthCheckResult":"Success","HealthCheckMessage":"All folders have the correct permissions set.","SourceContext":"Umbraco.Web.HealthCheck.HealthCheckResults","ProcessId":48900,"ProcessName":"iisexpress","ThreadId":32,"AppDomainId":2,"AppDomainAppId":"LMW3SVC2ROOT","MachineName":"CJ","Log4NetLevel":"INFO "}
{"@t":"2021-01-14T17:21:43.1072486Z","@mt":"Result for {HealthCheckName}: {HealthCheckResult}, Message: '{HealthCheckMessage}'","HealthCheckName":"Folder & File Permissions","HealthCheckResult":"Success","HealthCheckMessage":"All files have the correct permissions set.","SourceContext":"Umbraco.Web.HealthCheck.HealthCheckResults","ProcessId":48900,"ProcessName":"iisexpress","ThreadId":32,"AppDomainId":2,"AppDomainAppId":"LMW3SVC2ROOT","MachineName":"CJ","Log4NetLevel":"INFO "}
{"@t":"2021-01-14T17:21:43.1072486Z","@mt":"Checks for '{HealthCheckName}' completed with errors.","@l":"Warning","HealthCheckName":"SMTP Settings","SourceContext":"Umbraco.Web.HealthCheck.HealthCheckResults","ProcessId":48900,"ProcessName":"iisexpress","ThreadId":32,"AppDomainId":2,"AppDomainAppId":"LMW3SVC2ROOT","MachineName":"CJ","Log4NetLevel":"WARN "}
{"@t":"2021-01-14T17:21:43.1072486Z","@mt":"Result for {HealthCheckName}: {HealthCheckResult}, Message: '{HealthCheckMessage}'","HealthCheckName":"SMTP Settings","HealthCheckResult":"Error","HealthCheckMessage":"In the Web.config file system.net/mailsettings section, the host is not configured.","SourceContext":"Umbraco.Web.HealthCheck.HealthCheckResults","ProcessId":48900,"ProcessName":"iisexpress","ThreadId":32,"AppDomainId":2,"AppDomainAppId":"LMW3SVC2ROOT","MachineName":"CJ","Log4NetLevel":"INFO "}
{"@t":"2021-01-14T17:21:43.1072486Z","@mt":"Checks for '{HealthCheckName}' completed with errors.","@l":"Warning","HealthCheckName":"Macro errors","SourceContext":"Umbraco.Web.HealthCheck.HealthCheckResults","ProcessId":48900,"ProcessName":"iisexpress","ThreadId":32,"AppDomainId":2,"AppDomainAppId":"LMW3SVC2ROOT","MachineName":"CJ","Log4NetLevel":"WARN "}
{"@t":"2021-01-14T17:21:43.1072486Z","@mt":"Result for {HealthCheckName}: {HealthCheckResult}, Message: '{HealthCheckMessage}'","HealthCheckName":"Macro errors","HealthCheckResult":"Error","HealthCheckMessage":"MacroErrors are set to 'throw' which will prevent some or all pages in your site from loading completely if there are any errors in macros. Rectifying this will set the value to 'inline'.","SourceContext":"Umbraco.Web.HealthCheck.HealthCheckResults","ProcessId":48900,"ProcessName":"iisexpress","ThreadId":32,"AppDomainId":2,"AppDomainAppId":"LMW3SVC2ROOT","MachineName":"CJ","Log4NetLevel":"INFO "}
{"@t":"2021-01-14T17:21:43.1072486Z","@mt":"Checks for '{HealthCheckName}' completed with errors.","@l":"Warning","HealthCheckName":"Notification Email Settings","SourceContext":"Umbraco.Web.HealthCheck.HealthCheckResults","ProcessId":48900,"ProcessName":"iisexpress","ThreadId":32,"AppDomainId":2,"AppDomainAppId":"LMW3SVC2ROOT","MachineName":"CJ","Log4NetLevel":"WARN "}
{"@t":"2021-01-14T17:21:43.1072486Z","@mt":"Result for {HealthCheckName}: {HealthCheckResult}, Message: '{HealthCheckMessage}'","HealthCheckName":"Notification Email Settings","HealthCheckResult":"Error","HealthCheckMessage":"Notification email is still set to the default value of <strong>your@email.here</strong>.","SourceContext":"Umbraco.Web.HealthCheck.HealthCheckResults","ProcessId":48900,"ProcessName":"iisexpress","ThreadId":32,"AppDomainId":2,"AppDomainAppId":"LMW3SVC2ROOT","MachineName":"CJ","Log4NetLevel":"INFO "}
{"@t":"2021-01-14T17:21:43.1072486Z","@mt":"Checks for '{HealthCheckName}' all completed successfully.","HealthCheckName":"Try Skip IIS Custom Errors","SourceContext":"Umbraco.Web.HealthCheck.HealthCheckResults","ProcessId":48900,"ProcessName":"iisexpress","ThreadId":32,"AppDomainId":2,"AppDomainAppId":"LMW3SVC2ROOT","MachineName":"CJ","Log4NetLevel":"INFO "}
{"@t":"2021-01-14T17:21:43.1072486Z","@mt":"Result for {HealthCheckName}: {HealthCheckResult}, Message: '{HealthCheckMessage}'","HealthCheckName":"Try Skip IIS Custom Errors","HealthCheckResult":"Success","HealthCheckMessage":"Try Skip IIS Custom Errors is set to 'true' and you're using IIS version '10.0'.","SourceContext":"Umbraco.Web.HealthCheck.HealthCheckResults","ProcessId":48900,"ProcessName":"iisexpress","ThreadId":32,"AppDomainId":2,"AppDomainAppId":"LMW3SVC2ROOT","MachineName":"CJ","Log4NetLevel":"INFO "}
{"@t":"2021-01-14T17:21:43.1072486Z","@mt":"Checks for '{HealthCheckName}' all completed successfully.","HealthCheckName":"Custom Errors","SourceContext":"Umbraco.Web.HealthCheck.HealthCheckResults","ProcessId":48900,"ProcessName":"iisexpress","ThreadId":32,"AppDomainId":2,"AppDomainAppId":"LMW3SVC2ROOT","MachineName":"CJ","Log4NetLevel":"INFO "}
{"@t":"2021-01-14T17:21:43.1072486Z","@mt":"Result for {HealthCheckName}: {HealthCheckResult}, Message: '{HealthCheckMessage}'","HealthCheckName":"Custom Errors","HealthCheckResult":"Success","HealthCheckMessage":"Custom errors are set to 'RemoteOnly'.","SourceContext":"Umbraco.Web.HealthCheck.HealthCheckResults","ProcessId":48900,"ProcessName":"iisexpress","ThreadId":32,"AppDomainId":2,"AppDomainAppId":"LMW3SVC2ROOT","MachineName":"CJ","Log4NetLevel":"INFO "}
{"@t":"2021-01-14T17:21:43.1072486Z","@mt":"Checks for '{HealthCheckName}' all completed successfully.","HealthCheckName":"Trace Mode","SourceContext":"Umbraco.Web.HealthCheck.HealthCheckResults","ProcessId":48900,"ProcessName":"iisexpress","ThreadId":32,"AppDomainId":2,"AppDomainAppId":"LMW3SVC2ROOT","MachineName":"CJ","Log4NetLevel":"INFO "}
{"@t":"2021-01-14T17:21:43.1072486Z","@mt":"Result for {HealthCheckName}: {HealthCheckResult}, Message: '{HealthCheckMessage}'","HealthCheckName":"Trace Mode","HealthCheckResult":"Success","HealthCheckMessage":"Trace mode is disabled.","SourceContext":"Umbraco.Web.HealthCheck.HealthCheckResults","ProcessId":48900,"ProcessName":"iisexpress","ThreadId":32,"AppDomainId":2,"AppDomainAppId":"LMW3SVC2ROOT","MachineName":"CJ","Log4NetLevel":"INFO "}
{"@t":"2021-01-14T17:21:43.1072486Z","@mt":"Checks for '{HealthCheckName}' all completed successfully.","HealthCheckName":"Debug Compilation Mode","SourceContext":"Umbraco.Web.HealthCheck.HealthCheckResults","ProcessId":48900,"ProcessName":"iisexpress","ThreadId":32,"AppDomainId":2,"AppDomainAppId":"LMW3SVC2ROOT","MachineName":"CJ","Log4NetLevel":"INFO "}
{"@t":"2021-01-14T17:21:43.1072486Z","@mt":"Result for {HealthCheckName}: {HealthCheckResult}, Message: '{HealthCheckMessage}'","HealthCheckName":"Debug Compilation Mode","HealthCheckResult":"Success","HealthCheckMessage":"Debug compilation mode is disabled.","SourceContext":"Umbraco.Web.HealthCheck.HealthCheckResults","ProcessId":48900,"ProcessName":"iisexpress","ThreadId":32,"AppDomainId":2,"AppDomainAppId":"LMW3SVC2ROOT","MachineName":"CJ","Log4NetLevel":"INFO "}
{"@t":"2021-01-14T17:21:43.1072486Z","@mt":"Checks for '{HealthCheckName}' completed with errors.","@l":"Warning","HealthCheckName":"Cross-site scripting Protection (X-XSS-Protection header)","SourceContext":"Umbraco.Web.HealthCheck.HealthCheckResults","ProcessId":48900,"ProcessName":"iisexpress","ThreadId":32,"AppDomainId":2,"AppDomainAppId":"LMW3SVC2ROOT","MachineName":"CJ","Log4NetLevel":"WARN "}
{"@t":"2021-01-14T17:21:43.1072486Z","@mt":"Result for {HealthCheckName}: {HealthCheckResult}, Message: '{HealthCheckMessage}'","HealthCheckName":"Cross-site scripting Protection (X-XSS-Protection header)","HealthCheckResult":"Error","HealthCheckMessage":"The header <strong>X-XSS-Protection</strong> was not found.","SourceContext":"Umbraco.Web.HealthCheck.HealthCheckResults","ProcessId":48900,"ProcessName":"iisexpress","ThreadId":32,"AppDomainId":2,"AppDomainAppId":"LMW3SVC2ROOT","MachineName":"CJ","Log4NetLevel":"INFO "}
{"@t":"2021-01-14T17:21:43.1072486Z","@mt":"Checks for '{HealthCheckName}' completed with errors.","@l":"Warning","HealthCheckName":"Cookie hijacking and protocol downgrade attacks Protection (Strict-Transport-Security Header (HSTS))","SourceContext":"Umbraco.Web.HealthCheck.HealthCheckResults","ProcessId":48900,"ProcessName":"iisexpress","ThreadId":32,"AppDomainId":2,"AppDomainAppId":"LMW3SVC2ROOT","MachineName":"CJ","Log4NetLevel":"WARN "}
{"@t":"2021-01-14T17:21:43.1072486Z","@mt":"Result for {HealthCheckName}: {HealthCheckResult}, Message: '{HealthCheckMessage}'","HealthCheckName":"Cookie hijacking and protocol downgrade attacks Protection (Strict-Transport-Security Header (HSTS))","HealthCheckResult":"Error","HealthCheckMessage":"The header <strong>Strict-Transport-Security</strong> was not found.","SourceContext":"Umbraco.Web.HealthCheck.HealthCheckResults","ProcessId":48900,"ProcessName":"iisexpress","ThreadId":32,"AppDomainId":2,"AppDomainAppId":"LMW3SVC2ROOT","MachineName":"CJ","Log4NetLevel":"INFO "}
{"@t":"2021-01-14T17:21:43.1072486Z","@mt":"Checks for '{HealthCheckName}' completed with errors.","@l":"Warning","HealthCheckName":"Content/MIME Sniffing Protection","SourceContext":"Umbraco.Web.HealthCheck.HealthCheckResults","ProcessId":48900,"ProcessName":"iisexpress","ThreadId":32,"AppDomainId":2,"AppDomainAppId":"LMW3SVC2ROOT","MachineName":"CJ","Log4NetLevel":"WARN "}
{"@t":"2021-01-14T17:21:43.1072486Z","@mt":"Result for {HealthCheckName}: {HealthCheckResult}, Message: '{HealthCheckMessage}'","HealthCheckName":"Content/MIME Sniffing Protection","HealthCheckResult":"Error","HealthCheckMessage":"The header or meta-tag <strong>X-Content-Type-Options</strong> used to protect against MIME sniffing vulnerabilities was not found.","SourceContext":"Umbraco.Web.HealthCheck.HealthCheckResults","ProcessId":48900,"ProcessName":"iisexpress","ThreadId":32,"AppDomainId":2,"AppDomainAppId":"LMW3SVC2ROOT","MachineName":"CJ","Log4NetLevel":"INFO "}
{"@t":"2021-01-14T17:21:43.1072486Z","@mt":"Checks for '{HealthCheckName}' all completed successfully.","HealthCheckName":"Excessive Headers","SourceContext":"Umbraco.Web.HealthCheck.HealthCheckResults","ProcessId":48900,"ProcessName":"iisexpress","ThreadId":32,"AppDomainId":2,"AppDomainAppId":"LMW3SVC2ROOT","MachineName":"CJ","Log4NetLevel":"INFO "}
{"@t":"2021-01-14T17:21:43.1072486Z","@mt":"Result for {HealthCheckName}: {HealthCheckResult}, Message: '{HealthCheckMessage}'","HealthCheckName":"Excessive Headers","HealthCheckResult":"Success","HealthCheckMessage":"No headers revealing information about the website technology were found.","SourceContext":"Umbraco.Web.HealthCheck.HealthCheckResults","ProcessId":48900,"ProcessName":"iisexpress","ThreadId":32,"AppDomainId":2,"AppDomainAppId":"LMW3SVC2ROOT","MachineName":"CJ","Log4NetLevel":"INFO "}
{"@t":"2021-01-14T17:21:43.1072486Z","@mt":"Checks for '{HealthCheckName}' completed with errors.","@l":"Warning","HealthCheckName":"Click-Jacking Protection","SourceContext":"Umbraco.Web.HealthCheck.HealthCheckResults","ProcessId":48900,"ProcessName":"iisexpress","ThreadId":32,"AppDomainId":2,"AppDomainAppId":"LMW3SVC2ROOT","MachineName":"CJ","Log4NetLevel":"WARN "}
{"@t":"2021-01-14T17:21:43.1072486Z","@mt":"Result for {HealthCheckName}: {HealthCheckResult}, Message: '{HealthCheckMessage}'","HealthCheckName":"Click-Jacking Protection","HealthCheckResult":"Error","HealthCheckMessage":"The header or meta-tag <strong>X-Frame-Options</strong> used to control whether a site can be IFRAMEd by another was not found.","SourceContext":"Umbraco.Web.HealthCheck.HealthCheckResults","ProcessId":48900,"ProcessName":"iisexpress","ThreadId":32,"AppDomainId":2,"AppDomainAppId":"LMW3SVC2ROOT","MachineName":"CJ","Log4NetLevel":"INFO "}
{"@t":"2021-01-14T17:21:43.1072486Z","@mt":"Checks for '{HealthCheckName}' completed with errors.","@l":"Warning","HealthCheckName":"HTTPS Configuration","SourceContext":"Umbraco.Web.HealthCheck.HealthCheckResults","ProcessId":48900,"ProcessName":"iisexpress","ThreadId":32,"AppDomainId":2,"AppDomainAppId":"LMW3SVC2ROOT","MachineName":"CJ","Log4NetLevel":"WARN "}
{"@t":"2021-01-14T17:21:43.1072486Z","@mt":"Result for {HealthCheckName}: {HealthCheckResult}, Message: '{HealthCheckMessage}'","HealthCheckName":"HTTPS Configuration","HealthCheckResult":"Error","HealthCheckMessage":"You are currently not viewing the site using the HTTPS scheme.","SourceContext":"Umbraco.Web.HealthCheck.HealthCheckResults","ProcessId":48900,"ProcessName":"iisexpress","ThreadId":32,"AppDomainId":2,"AppDomainAppId":"LMW3SVC2ROOT","MachineName":"CJ","Log4NetLevel":"INFO "}
{"@t":"2021-01-14T17:21:43.1072486Z","@mt":"Result for {HealthCheckName}: {HealthCheckResult}, Message: '{HealthCheckMessage}'","HealthCheckName":"HTTPS Configuration","HealthCheckResult":"Info","HealthCheckMessage":"The appSetting 'Umbraco.Core.UseHttps' is set to 'false' in your web.config file. Once you access this site using the HTTPS scheme, that should be set to 'true'.","SourceContext":"Umbraco.Web.HealthCheck.HealthCheckResults","ProcessId":48900,"ProcessName":"iisexpress","ThreadId":32,"AppDomainId":2,"AppDomainAppId":"LMW3SVC2ROOT","MachineName":"CJ","Log4NetLevel":"INFO "}
{"@t":"2021-01-14T17:21:43.1072486Z","@mt":"Result for {HealthCheckName}: {HealthCheckResult}, Message: '{HealthCheckMessage}'","HealthCheckName":"HTTPS Configuration","HealthCheckResult":"Error","HealthCheckMessage":"Error pinging the URL https://localhost:58464/umbraco - 'The underlying connection was closed: An unexpected error occurred on a send.'","SourceContext":"Umbraco.Web.HealthCheck.HealthCheckResults","ProcessId":48900,"ProcessName":"iisexpress","ThreadId":32,"AppDomainId":2,"AppDomainAppId":"LMW3SVC2ROOT","MachineName":"CJ","Log4NetLevel":"INFO "}
{"@t":"2021-01-14T17:21:43.1072486Z","@mt":"Checks for '{HealthCheckName}' all completed successfully.","HealthCheckName":"Database data integrity check","SourceContext":"Umbraco.Web.HealthCheck.HealthCheckResults","ProcessId":48900,"ProcessName":"iisexpress","ThreadId":32,"AppDomainId":2,"AppDomainAppId":"LMW3SVC2ROOT","MachineName":"CJ","Log4NetLevel":"INFO "}
{"@t":"2021-01-14T17:21:43.1072486Z","@mt":"Result for {HealthCheckName}: {HealthCheckResult}, Message: '{HealthCheckMessage}'","HealthCheckName":"Database data integrity check","HealthCheckResult":"Success","HealthCheckMessage":"<p>All document paths are valid</p>\r\n","SourceContext":"Umbraco.Web.HealthCheck.HealthCheckResults","ProcessId":48900,"ProcessName":"iisexpress","ThreadId":32,"AppDomainId":2,"AppDomainAppId":"LMW3SVC2ROOT","MachineName":"CJ","Log4NetLevel":"INFO "}
{"@t":"2021-01-14T17:21:43.1072486Z","@mt":"Result for {HealthCheckName}: {HealthCheckResult}, Message: '{HealthCheckMessage}'","HealthCheckName":"Database data integrity check","HealthCheckResult":"Success","HealthCheckMessage":"<p>All media paths are valid</p>\r\n","SourceContext":"Umbraco.Web.HealthCheck.HealthCheckResults","ProcessId":48900,"ProcessName":"iisexpress","ThreadId":32,"AppDomainId":2,"AppDomainAppId":"LMW3SVC2ROOT","MachineName":"CJ","Log4NetLevel":"INFO "}
{"@t":"2021-01-14T17:21:55.7295904Z","@mt":"{StartMessage} [Timing {TimingId}]","StartMessage":"Loading content from database","TimingId":"73057da","SourceContext":"Umbraco.Web.PublishedCache.NuCache.PublishedSnapshotService","ProcessId":48900,"ProcessName":"iisexpress","ThreadId":17,"AppDomainId":2,"AppDomainAppId":"LMW3SVC2ROOT","MachineName":"CJ","Log4NetLevel":"INFO ","HttpRequestNumber":7,"HttpRequestId":"29588415-07ca-4af7-a8c4-124bc7f2930e"}
{"@t":"2021-01-14T17:21:55.8832861Z","@mt":"{EndMessage} ({Duration}ms) [Timing {TimingId}]","EndMessage":"Completed.","Duration":153,"TimingId":"73057da","SourceContext":"Umbraco.Web.PublishedCache.NuCache.PublishedSnapshotService","ProcessId":48900,"ProcessName":"iisexpress","ThreadId":17,"AppDomainId":2,"AppDomainAppId":"LMW3SVC2ROOT","MachineName":"CJ","Log4NetLevel":"INFO ","HttpRequestNumber":7,"HttpRequestId":"29588415-07ca-4af7-a8c4-124bc7f2930e"}
{"@t":"2021-01-14T17:21:55.9151825Z","@mt":"{StartMessage} [Timing {TimingId}]","StartMessage":"Loading media from database","TimingId":"8a482f0","SourceContext":"Umbraco.Web.PublishedCache.NuCache.PublishedSnapshotService","ProcessId":48900,"ProcessName":"iisexpress","ThreadId":17,"AppDomainId":2,"AppDomainAppId":"LMW3SVC2ROOT","MachineName":"CJ","Log4NetLevel":"INFO ","HttpRequestNumber":7,"HttpRequestId":"29588415-07ca-4af7-a8c4-124bc7f2930e"}
{"@t":"2021-01-14T17:21:56.0494169Z","@mt":"{EndMessage} ({Duration}ms) [Timing {TimingId}]","EndMessage":"Completed.","Duration":134,"TimingId":"8a482f0","SourceContext":"Umbraco.Web.PublishedCache.NuCache.PublishedSnapshotService","ProcessId":48900,"ProcessName":"iisexpress","ThreadId":17,"AppDomainId":2,"AppDomainAppId":"LMW3SVC2ROOT","MachineName":"CJ","Log4NetLevel":"INFO ","HttpRequestNumber":7,"HttpRequestId":"29588415-07ca-4af7-a8c4-124bc7f2930e"}
{"@t":"2021-01-14T17:22:00.0916811Z","@mt":"{StartMessage} [Timing {TimingId}]","StartMessage":"Loading content from database","TimingId":"2c6234c","SourceContext":"Umbraco.Web.PublishedCache.NuCache.PublishedSnapshotService","ProcessId":48900,"ProcessName":"iisexpress","ThreadId":19,"AppDomainId":2,"AppDomainAppId":"LMW3SVC2ROOT","MachineName":"CJ","Log4NetLevel":"INFO ","HttpRequestNumber":8,"HttpRequestId":"f0d70081-18b4-45c4-857a-45afa73f342c"}
{"@t":"2021-01-14T17:22:00.2386087Z","@mt":"{EndMessage} ({Duration}ms) [Timing {TimingId}]","EndMessage":"Completed.","Duration":147,"TimingId":"2c6234c","SourceContext":"Umbraco.Web.PublishedCache.NuCache.PublishedSnapshotService","ProcessId":48900,"ProcessName":"iisexpress","ThreadId":19,"AppDomainId":2,"AppDomainAppId":"LMW3SVC2ROOT","MachineName":"CJ","Log4NetLevel":"INFO ","HttpRequestNumber":8,"HttpRequestId":"f0d70081-18b4-45c4-857a-45afa73f342c"}
{"@t":"2021-01-14T17:22:00.2685288Z","@mt":"{StartMessage} [Timing {TimingId}]","StartMessage":"Loading media from database","TimingId":"832009c","SourceContext":"Umbraco.Web.PublishedCache.NuCache.PublishedSnapshotService","ProcessId":48900,"ProcessName":"iisexpress","ThreadId":19,"AppDomainId":2,"AppDomainAppId":"LMW3SVC2ROOT","MachineName":"CJ","Log4NetLevel":"INFO ","HttpRequestNumber":8,"HttpRequestId":"f0d70081-18b4-45c4-857a-45afa73f342c"}
{"@t":"2021-01-14T17:22:00.3986429Z","@mt":"{EndMessage} ({Duration}ms) [Timing {TimingId}]","EndMessage":"Completed.","Duration":130,"TimingId":"832009c","SourceContext":"Umbraco.Web.PublishedCache.NuCache.PublishedSnapshotService","ProcessId":48900,"ProcessName":"iisexpress","ThreadId":19,"AppDomainId":2,"AppDomainAppId":"LMW3SVC2ROOT","MachineName":"CJ","Log4NetLevel":"INFO ","HttpRequestNumber":8,"HttpRequestId":"f0d70081-18b4-45c4-857a-45afa73f342c"}
{"@t":"2021-01-14T17:22:13.7409544Z","@mt":"{StartMessage} [Timing {TimingId}]","StartMessage":"Loading content from database","TimingId":"ffeeb79","SourceContext":"Umbraco.Web.PublishedCache.NuCache.PublishedSnapshotService","ProcessId":48900,"ProcessName":"iisexpress","ThreadId":30,"AppDomainId":2,"AppDomainAppId":"LMW3SVC2ROOT","MachineName":"CJ","Log4NetLevel":"INFO ","HttpRequestNumber":9,"HttpRequestId":"228c4d0a-e197-4501-8f78-1dd686988069"}
{"@t":"2021-01-14T17:22:13.8819570Z","@mt":"{EndMessage} ({Duration}ms) [Timing {TimingId}]","EndMessage":"Completed.","Duration":141,"TimingId":"ffeeb79","SourceContext":"Umbraco.Web.PublishedCache.NuCache.PublishedSnapshotService","ProcessId":48900,"ProcessName":"iisexpress","ThreadId":30,"AppDomainId":2,"AppDomainAppId":"LMW3SVC2ROOT","MachineName":"CJ","Log4NetLevel":"INFO ","HttpRequestNumber":9,"HttpRequestId":"228c4d0a-e197-4501-8f78-1dd686988069"}
{"@t":"2021-01-14T17:22:13.9138710Z","@mt":"{StartMessage} [Timing {TimingId}]","StartMessage":"Loading media from database","TimingId":"44a2e26","SourceContext":"Umbraco.Web.PublishedCache.NuCache.PublishedSnapshotService","ProcessId":48900,"ProcessName":"iisexpress","ThreadId":30,"AppDomainId":2,"AppDomainAppId":"LMW3SVC2ROOT","MachineName":"CJ","Log4NetLevel":"INFO ","HttpRequestNumber":9,"HttpRequestId":"228c4d0a-e197-4501-8f78-1dd686988069"}
{"@t":"2021-01-14T17:22:14.0397584Z","@mt":"{EndMessage} ({Duration}ms) [Timing {TimingId}]","EndMessage":"Completed.","Duration":126,"TimingId":"44a2e26","SourceContext":"Umbraco.Web.PublishedCache.NuCache.PublishedSnapshotService","ProcessId":48900,"ProcessName":"iisexpress","ThreadId":30,"AppDomainId":2,"AppDomainAppId":"LMW3SVC2ROOT","MachineName":"CJ","Log4NetLevel":"INFO ","HttpRequestNumber":9,"HttpRequestId":"228c4d0a-e197-4501-8f78-1dd686988069"}
{"@t":"2021-01-14T17:22:40.0762591Z","@mt":"Unhandled controller exception occurred for request '{RequestUrl}'","@l":"Error","@x":"System.Web.Http.HttpResponseException: Processing of the HTTP request resulted in an exception. Please see the HTTP response returned by the 'Response' property of this exception for details.\r\n   at Umbraco.Web.WebApi.Filters.EnsureUserPermissionForContentAttribute.OnActionExecuting(HttpActionContext actionContext) in D:\\a\\1\\s\\src\\Umbraco.Web\\WebApi\\Filters\\EnsureUserPermissionForContentAttribute.cs:line 127\r\n   at System.Web.Http.Filters.ActionFilterAttribute.OnActionExecutingAsync(HttpActionContext actionContext, CancellationToken cancellationToken)\r\n--- End of stack trace from previous location where exception was thrown ---\r\n   at System.Runtime.CompilerServices.TaskAwaiter.ThrowForNonSuccess(Task task)\r\n   at System.Runtime.CompilerServices.TaskAwaiter.HandleNonSuccessAndDebuggerNotification(Task task)\r\n   at System.Web.Http.Filters.ActionFilterAttribute.<ExecuteActionFilterAsyncCore>d__5.MoveNext()\r\n--- End of stack trace from previous location where exception was thrown ---\r\n   at System.Runtime.CompilerServices.TaskAwaiter.ThrowForNonSuccess(Task task)\r\n   at System.Runtime.CompilerServices.TaskAwaiter.HandleNonSuccessAndDebuggerNotification(Task task)\r\n   at System.Web.Http.Filters.ActionFilterAttribute.<CallOnActionExecutedAsync>d__6.MoveNext()\r\n--- End of stack trace from previous location where exception was thrown ---\r\n   at System.Web.Http.Filters.ActionFilterAttribute.<CallOnActionExecutedAsync>d__6.MoveNext()\r\n--- End of stack trace from previous location where exception was thrown ---\r\n   at System.Runtime.CompilerServices.TaskAwaiter.ThrowForNonSuccess(Task task)\r\n   at System.Runtime.CompilerServices.TaskAwaiter.HandleNonSuccessAndDebuggerNotification(Task task)\r\n   at System.Web.Http.Filters.ActionFilterAttribute.<ExecuteActionFilterAsyncCore>d__5.MoveNext()\r\n--- End of stack trace from previous location where exception was thrown ---\r\n   at System.Runtime.CompilerServices.TaskAwaiter.ThrowForNonSuccess(Task task)\r\n   at System.Runtime.CompilerServices.TaskAwaiter.HandleNonSuccessAndDebuggerNotification(Task task)\r\n   at System.Web.Http.Filters.ActionFilterAttribute.<CallOnActionExecutedAsync>d__6.MoveNext()\r\n--- End of stack trace from previous location where exception was thrown ---\r\n   at System.Web.Http.Filters.ActionFilterAttribute.<CallOnActionExecutedAsync>d__6.MoveNext()\r\n--- End of stack trace from previous location where exception was thrown ---\r\n   at System.Runtime.CompilerServices.TaskAwaiter.ThrowForNonSuccess(Task task)\r\n   at System.Runtime.CompilerServices.TaskAwaiter.HandleNonSuccessAndDebuggerNotification(Task task)\r\n   at System.Web.Http.Filters.ActionFilterAttribute.<ExecuteActionFilterAsyncCore>d__5.MoveNext()\r\n--- End of stack trace from previous location where exception was thrown ---\r\n   at System.Runtime.CompilerServices.TaskAwaiter.ThrowForNonSuccess(Task task)\r\n   at System.Runtime.CompilerServices.TaskAwaiter.HandleNonSuccessAndDebuggerNotification(Task task)\r\n   at System.Web.Http.Filters.ActionFilterAttribute.<CallOnActionExecutedAsync>d__6.MoveNext()\r\n--- End of stack trace from previous location where exception was thrown ---\r\n   at System.Web.Http.Filters.ActionFilterAttribute.<CallOnActionExecutedAsync>d__6.MoveNext()\r\n--- End of stack trace from previous location where exception was thrown ---\r\n   at System.Runtime.CompilerServices.TaskAwaiter.ThrowForNonSuccess(Task task)\r\n   at System.Runtime.CompilerServices.TaskAwaiter.HandleNonSuccessAndDebuggerNotification(Task task)\r\n   at System.Web.Http.Filters.ActionFilterAttribute.<ExecuteActionFilterAsyncCore>d__5.MoveNext()\r\n--- End of stack trace from previous location where exception was thrown ---\r\n   at System.Runtime.CompilerServices.TaskAwaiter.ThrowForNonSuccess(Task task)\r\n   at System.Runtime.CompilerServices.TaskAwaiter.HandleNonSuccessAndDebuggerNotification(Task task)\r\n   at System.Web.Http.Filters.ActionFilterAttribute.<CallOnActionExecutedAsync>d__6.MoveNext()\r\n--- End of stack trace from previous location where exception was thrown ---\r\n   at System.Web.Http.Filters.ActionFilterAttribute.<CallOnActionExecutedAsync>d__6.MoveNext()\r\n--- End of stack trace from previous location where exception was thrown ---\r\n   at System.Runtime.CompilerServices.TaskAwaiter.ThrowForNonSuccess(Task task)\r\n   at System.Runtime.CompilerServices.TaskAwaiter.HandleNonSuccessAndDebuggerNotification(Task task)\r\n   at System.Web.Http.Filters.ActionFilterAttribute.<ExecuteActionFilterAsyncCore>d__5.MoveNext()\r\n--- End of stack trace from previous location where exception was thrown ---\r\n   at System.Runtime.CompilerServices.TaskAwaiter.ThrowForNonSuccess(Task task)\r\n   at System.Runtime.CompilerServices.TaskAwaiter.HandleNonSuccessAndDebuggerNotification(Task task)\r\n   at System.Web.Http.Filters.ActionFilterAttribute.<CallOnActionExecutedAsync>d__6.MoveNext()\r\n--- End of stack trace from previous location where exception was thrown ---\r\n   at System.Web.Http.Filters.ActionFilterAttribute.<CallOnActionExecutedAsync>d__6.MoveNext()\r\n--- End of stack trace from previous location where exception was thrown ---\r\n   at System.Runtime.CompilerServices.TaskAwaiter.ThrowForNonSuccess(Task task)\r\n   at System.Runtime.CompilerServices.TaskAwaiter.HandleNonSuccessAndDebuggerNotification(Task task)\r\n   at System.Web.Http.Filters.ActionFilterAttribute.<ExecuteActionFilterAsyncCore>d__5.MoveNext()\r\n--- End of stack trace from previous location where exception was thrown ---\r\n   at System.Runtime.CompilerServices.TaskAwaiter.ThrowForNonSuccess(Task task)\r\n   at System.Runtime.CompilerServices.TaskAwaiter.HandleNonSuccessAndDebuggerNotification(Task task)\r\n   at System.Web.Http.Filters.ActionFilterAttribute.<CallOnActionExecutedAsync>d__6.MoveNext()\r\n--- End of stack trace from previous location where exception was thrown ---\r\n   at System.Web.Http.Filters.ActionFilterAttribute.<CallOnActionExecutedAsync>d__6.MoveNext()\r\n--- End of stack trace from previous location where exception was thrown ---\r\n   at System.Runtime.CompilerServices.TaskAwaiter.ThrowForNonSuccess(Task task)\r\n   at System.Runtime.CompilerServices.TaskAwaiter.HandleNonSuccessAndDebuggerNotification(Task task)\r\n   at System.Web.Http.Filters.ActionFilterAttribute.<ExecuteActionFilterAsyncCore>d__5.MoveNext()\r\n--- End of stack trace from previous location where exception was thrown ---\r\n   at System.Runtime.CompilerServices.TaskAwaiter.ThrowForNonSuccess(Task task)\r\n   at System.Runtime.CompilerServices.TaskAwaiter.HandleNonSuccessAndDebuggerNotification(Task task)\r\n   at System.Web.Http.Filters.ActionFilterAttribute.<CallOnActionExecutedAsync>d__6.MoveNext()\r\n--- End of stack trace from previous location where exception was thrown ---\r\n   at System.Web.Http.Filters.ActionFilterAttribute.<CallOnActionExecutedAsync>d__6.MoveNext()\r\n--- End of stack trace from previous location where exception was thrown ---\r\n   at System.Runtime.CompilerServices.TaskAwaiter.ThrowForNonSuccess(Task task)\r\n   at System.Runtime.CompilerServices.TaskAwaiter.HandleNonSuccessAndDebuggerNotification(Task task)\r\n   at System.Web.Http.Filters.ActionFilterAttribute.<ExecuteActionFilterAsyncCore>d__5.MoveNext()\r\n--- End of stack trace from previous location where exception was thrown ---\r\n   at System.Runtime.CompilerServices.TaskAwaiter.ThrowForNonSuccess(Task task)\r\n   at System.Runtime.CompilerServices.TaskAwaiter.HandleNonSuccessAndDebuggerNotification(Task task)\r\n   at System.Web.Http.Controllers.ActionFilterResult.<ExecuteAsync>d__5.MoveNext()\r\n--- End of stack trace from previous location where exception was thrown ---\r\n   at System.Runtime.CompilerServices.TaskAwaiter.ThrowForNonSuccess(Task task)\r\n   at System.Runtime.CompilerServices.TaskAwaiter.HandleNonSuccessAndDebuggerNotification(Task task)\r\n   at System.Web.Http.Filters.AuthorizationFilterAttribute.<ExecuteAuthorizationFilterAsyncCore>d__3.MoveNext()\r\n--- End of stack trace from previous location where exception was thrown ---\r\n   at System.Runtime.CompilerServices.TaskAwaiter.ThrowForNonSuccess(Task task)\r\n   at System.Runtime.CompilerServices.TaskAwaiter.HandleNonSuccessAndDebuggerNotification(Task task)\r\n   at System.Web.Http.Filters.AuthorizationFilterAttribute.<ExecuteAuthorizationFilterAsyncCore>d__3.MoveNext()\r\n--- End of stack trace from previous location where exception was thrown ---\r\n   at System.Runtime.CompilerServices.TaskAwaiter.ThrowForNonSuccess(Task task)\r\n   at System.Runtime.CompilerServices.TaskAwaiter.HandleNonSuccessAndDebuggerNotification(Task task)\r\n   at System.Web.Http.Filters.AuthorizationFilterAttribute.<ExecuteAuthorizationFilterAsyncCore>d__3.MoveNext()\r\n--- End of stack trace from previous location where exception was thrown ---\r\n   at System.Runtime.CompilerServices.TaskAwaiter.ThrowForNonSuccess(Task task)\r\n   at System.Runtime.CompilerServices.TaskAwaiter.HandleNonSuccessAndDebuggerNotification(Task task)\r\n   at System.Web.Http.Filters.AuthorizationFilterAttribute.<ExecuteAuthorizationFilterAsyncCore>d__3.MoveNext()\r\n--- End of stack trace from previous location where exception was thrown ---\r\n   at System.Runtime.CompilerServices.TaskAwaiter.ThrowForNonSuccess(Task task)\r\n   at System.Runtime.CompilerServices.TaskAwaiter.HandleNonSuccessAndDebuggerNotification(Task task)\r\n   at System.Web.Http.Controllers.ExceptionFilterResult.<ExecuteAsync>d__6.MoveNext()","RequestUrl":"http://localhost:58464/umbraco/backoffice/UmbracoApi/Content/GetById?id=1148","SourceContext":"Umbraco.Web.Editors.ContentController","ProcessId":48900,"ProcessName":"iisexpress","ThreadId":49,"AppDomainId":2,"AppDomainAppId":"LMW3SVC2ROOT","MachineName":"CJ","Log4NetLevel":"ERROR","HttpRequestNumber":10,"HttpRequestId":"5015c800-bdb4-4cb5-85de-f31d5b4ba43d"}
{"@t":"2021-01-14T17:22:50.8042513Z","@mt":"Unhandled controller exception occurred for request '{RequestUrl}'","@l":"Error","@x":"System.Web.Http.HttpResponseException: Processing of the HTTP request resulted in an exception. Please see the HTTP response returned by the 'Response' property of this exception for details.\r\n   at Umbraco.Web.WebApi.Filters.EnsureUserPermissionForContentAttribute.OnActionExecuting(HttpActionContext actionContext) in D:\\a\\1\\s\\src\\Umbraco.Web\\WebApi\\Filters\\EnsureUserPermissionForContentAttribute.cs:line 127\r\n   at System.Web.Http.Filters.ActionFilterAttribute.OnActionExecutingAsync(HttpActionContext actionContext, CancellationToken cancellationToken)\r\n--- End of stack trace from previous location where exception was thrown ---\r\n   at System.Runtime.CompilerServices.TaskAwaiter.ThrowForNonSuccess(Task task)\r\n   at System.Runtime.CompilerServices.TaskAwaiter.HandleNonSuccessAndDebuggerNotification(Task task)\r\n   at System.Web.Http.Filters.ActionFilterAttribute.<ExecuteActionFilterAsyncCore>d__5.MoveNext()\r\n--- End of stack trace from previous location where exception was thrown ---\r\n   at System.Runtime.CompilerServices.TaskAwaiter.ThrowForNonSuccess(Task task)\r\n   at System.Runtime.CompilerServices.TaskAwaiter.HandleNonSuccessAndDebuggerNotification(Task task)\r\n   at System.Web.Http.Filters.ActionFilterAttribute.<CallOnActionExecutedAsync>d__6.MoveNext()\r\n--- End of stack trace from previous location where exception was thrown ---\r\n   at System.Web.Http.Filters.ActionFilterAttribute.<CallOnActionExecutedAsync>d__6.MoveNext()\r\n--- End of stack trace from previous location where exception was thrown ---\r\n   at System.Runtime.CompilerServices.TaskAwaiter.ThrowForNonSuccess(Task task)\r\n   at System.Runtime.CompilerServices.TaskAwaiter.HandleNonSuccessAndDebuggerNotification(Task task)\r\n   at System.Web.Http.Filters.ActionFilterAttribute.<ExecuteActionFilterAsyncCore>d__5.MoveNext()\r\n--- End of stack trace from previous location where exception was thrown ---\r\n   at System.Runtime.CompilerServices.TaskAwaiter.ThrowForNonSuccess(Task task)\r\n   at System.Runtime.CompilerServices.TaskAwaiter.HandleNonSuccessAndDebuggerNotification(Task task)\r\n   at System.Web.Http.Filters.ActionFilterAttribute.<CallOnActionExecutedAsync>d__6.MoveNext()\r\n--- End of stack trace from previous location where exception was thrown ---\r\n   at System.Web.Http.Filters.ActionFilterAttribute.<CallOnActionExecutedAsync>d__6.MoveNext()\r\n--- End of stack trace from previous location where exception was thrown ---\r\n   at System.Runtime.CompilerServices.TaskAwaiter.ThrowForNonSuccess(Task task)\r\n   at System.Runtime.CompilerServices.TaskAwaiter.HandleNonSuccessAndDebuggerNotification(Task task)\r\n   at System.Web.Http.Filters.ActionFilterAttribute.<ExecuteActionFilterAsyncCore>d__5.MoveNext()\r\n--- End of stack trace from previous location where exception was thrown ---\r\n   at System.Runtime.CompilerServices.TaskAwaiter.ThrowForNonSuccess(Task task)\r\n   at System.Runtime.CompilerServices.TaskAwaiter.HandleNonSuccessAndDebuggerNotification(Task task)\r\n   at System.Web.Http.Filters.ActionFilterAttribute.<CallOnActionExecutedAsync>d__6.MoveNext()\r\n--- End of stack trace from previous location where exception was thrown ---\r\n   at System.Web.Http.Filters.ActionFilterAttribute.<CallOnActionExecutedAsync>d__6.MoveNext()\r\n--- End of stack trace from previous location where exception was thrown ---\r\n   at System.Runtime.CompilerServices.TaskAwaiter.ThrowForNonSuccess(Task task)\r\n   at System.Runtime.CompilerServices.TaskAwaiter.HandleNonSuccessAndDebuggerNotification(Task task)\r\n   at System.Web.Http.Filters.ActionFilterAttribute.<ExecuteActionFilterAsyncCore>d__5.MoveNext()\r\n--- End of stack trace from previous location where exception was thrown ---\r\n   at System.Runtime.CompilerServices.TaskAwaiter.ThrowForNonSuccess(Task task)\r\n   at System.Runtime.CompilerServices.TaskAwaiter.HandleNonSuccessAndDebuggerNotification(Task task)\r\n   at System.Web.Http.Filters.ActionFilterAttribute.<CallOnActionExecutedAsync>d__6.MoveNext()\r\n--- End of stack trace from previous location where exception was thrown ---\r\n   at System.Web.Http.Filters.ActionFilterAttribute.<CallOnActionExecutedAsync>d__6.MoveNext()\r\n--- End of stack trace from previous location where exception was thrown ---\r\n   at System.Runtime.CompilerServices.TaskAwaiter.ThrowForNonSuccess(Task task)\r\n   at System.Runtime.CompilerServices.TaskAwaiter.HandleNonSuccessAndDebuggerNotification(Task task)\r\n   at System.Web.Http.Filters.ActionFilterAttribute.<ExecuteActionFilterAsyncCore>d__5.MoveNext()\r\n--- End of stack trace from previous location where exception was thrown ---\r\n   at System.Runtime.CompilerServices.TaskAwaiter.ThrowForNonSuccess(Task task)\r\n   at System.Runtime.CompilerServices.TaskAwaiter.HandleNonSuccessAndDebuggerNotification(Task task)\r\n   at System.Web.Http.Filters.ActionFilterAttribute.<CallOnActionExecutedAsync>d__6.MoveNext()\r\n--- End of stack trace from previous location where exception was thrown ---\r\n   at System.Web.Http.Filters.ActionFilterAttribute.<CallOnActionExecutedAsync>d__6.MoveNext()\r\n--- End of stack trace from previous location where exception was thrown ---\r\n   at System.Runtime.CompilerServices.TaskAwaiter.ThrowForNonSuccess(Task task)\r\n   at System.Runtime.CompilerServices.TaskAwaiter.HandleNonSuccessAndDebuggerNotification(Task task)\r\n   at System.Web.Http.Filters.ActionFilterAttribute.<ExecuteActionFilterAsyncCore>d__5.MoveNext()\r\n--- End of stack trace from previous location where exception was thrown ---\r\n   at System.Runtime.CompilerServices.TaskAwaiter.ThrowForNonSuccess(Task task)\r\n   at System.Runtime.CompilerServices.TaskAwaiter.HandleNonSuccessAndDebuggerNotification(Task task)\r\n   at System.Web.Http.Filters.ActionFilterAttribute.<CallOnActionExecutedAsync>d__6.MoveNext()\r\n--- End of stack trace from previous location where exception was thrown ---\r\n   at System.Web.Http.Filters.ActionFilterAttribute.<CallOnActionExecutedAsync>d__6.MoveNext()\r\n--- End of stack trace from previous location where exception was thrown ---\r\n   at System.Runtime.CompilerServices.TaskAwaiter.ThrowForNonSuccess(Task task)\r\n   at System.Runtime.CompilerServices.TaskAwaiter.HandleNonSuccessAndDebuggerNotification(Task task)\r\n   at System.Web.Http.Filters.ActionFilterAttribute.<ExecuteActionFilterAsyncCore>d__5.MoveNext()\r\n--- End of stack trace from previous location where exception was thrown ---\r\n   at System.Runtime.CompilerServices.TaskAwaiter.ThrowForNonSuccess(Task task)\r\n   at System.Runtime.CompilerServices.TaskAwaiter.HandleNonSuccessAndDebuggerNotification(Task task)\r\n   at System.Web.Http.Filters.ActionFilterAttribute.<CallOnActionExecutedAsync>d__6.MoveNext()\r\n--- End of stack trace from previous location where exception was thrown ---\r\n   at System.Web.Http.Filters.ActionFilterAttribute.<CallOnActionExecutedAsync>d__6.MoveNext()\r\n--- End of stack trace from previous location where exception was thrown ---\r\n   at System.Runtime.CompilerServices.TaskAwaiter.ThrowForNonSuccess(Task task)\r\n   at System.Runtime.CompilerServices.TaskAwaiter.HandleNonSuccessAndDebuggerNotification(Task task)\r\n   at System.Web.Http.Filters.ActionFilterAttribute.<ExecuteActionFilterAsyncCore>d__5.MoveNext()\r\n--- End of stack trace from previous location where exception was thrown ---\r\n   at System.Runtime.CompilerServices.TaskAwaiter.ThrowForNonSuccess(Task task)\r\n   at System.Runtime.CompilerServices.TaskAwaiter.HandleNonSuccessAndDebuggerNotification(Task task)\r\n   at System.Web.Http.Controllers.ActionFilterResult.<ExecuteAsync>d__5.MoveNext()\r\n--- End of stack trace from previous location where exception was thrown ---\r\n   at System.Runtime.CompilerServices.TaskAwaiter.ThrowForNonSuccess(Task task)\r\n   at System.Runtime.CompilerServices.TaskAwaiter.HandleNonSuccessAndDebuggerNotification(Task task)\r\n   at System.Web.Http.Filters.AuthorizationFilterAttribute.<ExecuteAuthorizationFilterAsyncCore>d__3.MoveNext()\r\n--- End of stack trace from previous location where exception was thrown ---\r\n   at System.Runtime.CompilerServices.TaskAwaiter.ThrowForNonSuccess(Task task)\r\n   at System.Runtime.CompilerServices.TaskAwaiter.HandleNonSuccessAndDebuggerNotification(Task task)\r\n   at System.Web.Http.Filters.AuthorizationFilterAttribute.<ExecuteAuthorizationFilterAsyncCore>d__3.MoveNext()\r\n--- End of stack trace from previous location where exception was thrown ---\r\n   at System.Runtime.CompilerServices.TaskAwaiter.ThrowForNonSuccess(Task task)\r\n   at System.Runtime.CompilerServices.TaskAwaiter.HandleNonSuccessAndDebuggerNotification(Task task)\r\n   at System.Web.Http.Filters.AuthorizationFilterAttribute.<ExecuteAuthorizationFilterAsyncCore>d__3.MoveNext()\r\n--- End of stack trace from previous location where exception was thrown ---\r\n   at System.Runtime.CompilerServices.TaskAwaiter.ThrowForNonSuccess(Task task)\r\n   at System.Runtime.CompilerServices.TaskAwaiter.HandleNonSuccessAndDebuggerNotification(Task task)\r\n   at System.Web.Http.Filters.AuthorizationFilterAttribute.<ExecuteAuthorizationFilterAsyncCore>d__3.MoveNext()\r\n--- End of stack trace from previous location where exception was thrown ---\r\n   at System.Runtime.CompilerServices.TaskAwaiter.ThrowForNonSuccess(Task task)\r\n   at System.Runtime.CompilerServices.TaskAwaiter.HandleNonSuccessAndDebuggerNotification(Task task)\r\n   at System.Web.Http.Controllers.ExceptionFilterResult.<ExecuteAsync>d__6.MoveNext()\r\n--- End of stack trace from previous location where exception was thrown ---\r\n   at System.Web.Http.Controllers.ExceptionFilterResult.<ExecuteAsync>d__6.MoveNext()\r\n--- End of stack trace from previous location where exception was thrown ---\r\n   at System.Runtime.CompilerServices.TaskAwaiter.ThrowForNonSuccess(Task task)\r\n   at System.Runtime.CompilerServices.TaskAwaiter.HandleNonSuccessAndDebuggerNotification(Task task)\r\n   at System.Web.Http.Dispatcher.HttpControllerDispatcher.<SendAsync>d__15.MoveNext()","RequestUrl":"http://localhost:58464/umbraco/backoffice/UmbracoApi/Content/GetById?id=1148","SourceContext":"Umbraco.Web.Editors.ContentController","ProcessId":48900,"ProcessName":"iisexpress","ThreadId":61,"AppDomainId":2,"AppDomainAppId":"LMW3SVC2ROOT","MachineName":"CJ","Log4NetLevel":"ERROR","HttpRequestNumber":11,"HttpRequestId":"c698b563-4332-4975-9728-779549f31909"}
{"@t":"2021-01-14T17:22:56.9998440Z","@mt":"Unhandled controller exception occurred for request '{RequestUrl}'","@l":"Error","@x":"System.Web.Http.HttpResponseException: Processing of the HTTP request resulted in an exception. Please see the HTTP response returned by the 'Response' property of this exception for details.\r\n   at Umbraco.Web.WebApi.Filters.EnsureUserPermissionForContentAttribute.OnActionExecuting(HttpActionContext actionContext) in D:\\a\\1\\s\\src\\Umbraco.Web\\WebApi\\Filters\\EnsureUserPermissionForContentAttribute.cs:line 127\r\n   at System.Web.Http.Filters.ActionFilterAttribute.OnActionExecutingAsync(HttpActionContext actionContext, CancellationToken cancellationToken)\r\n--- End of stack trace from previous location where exception was thrown ---\r\n   at System.Runtime.CompilerServices.TaskAwaiter.ThrowForNonSuccess(Task task)\r\n   at System.Runtime.CompilerServices.TaskAwaiter.HandleNonSuccessAndDebuggerNotification(Task task)\r\n   at System.Web.Http.Filters.ActionFilterAttribute.<ExecuteActionFilterAsyncCore>d__5.MoveNext()\r\n--- End of stack trace from previous location where exception was thrown ---\r\n   at System.Runtime.CompilerServices.TaskAwaiter.ThrowForNonSuccess(Task task)\r\n   at System.Runtime.CompilerServices.TaskAwaiter.HandleNonSuccessAndDebuggerNotification(Task task)\r\n   at System.Web.Http.Filters.ActionFilterAttribute.<CallOnActionExecutedAsync>d__6.MoveNext()\r\n--- End of stack trace from previous location where exception was thrown ---\r\n   at System.Web.Http.Filters.ActionFilterAttribute.<CallOnActionExecutedAsync>d__6.MoveNext()\r\n--- End of stack trace from previous location where exception was thrown ---\r\n   at System.Runtime.CompilerServices.TaskAwaiter.ThrowForNonSuccess(Task task)\r\n   at System.Runtime.CompilerServices.TaskAwaiter.HandleNonSuccessAndDebuggerNotification(Task task)\r\n   at System.Web.Http.Filters.ActionFilterAttribute.<ExecuteActionFilterAsyncCore>d__5.MoveNext()\r\n--- End of stack trace from previous location where exception was thrown ---\r\n   at System.Runtime.CompilerServices.TaskAwaiter.ThrowForNonSuccess(Task task)\r\n   at System.Runtime.CompilerServices.TaskAwaiter.HandleNonSuccessAndDebuggerNotification(Task task)\r\n   at System.Web.Http.Filters.ActionFilterAttribute.<CallOnActionExecutedAsync>d__6.MoveNext()\r\n--- End of stack trace from previous location where exception was thrown ---\r\n   at System.Web.Http.Filters.ActionFilterAttribute.<CallOnActionExecutedAsync>d__6.MoveNext()\r\n--- End of stack trace from previous location where exception was thrown ---\r\n   at System.Runtime.CompilerServices.TaskAwaiter.ThrowForNonSuccess(Task task)\r\n   at System.Runtime.CompilerServices.TaskAwaiter.HandleNonSuccessAndDebuggerNotification(Task task)\r\n   at System.Web.Http.Filters.ActionFilterAttribute.<ExecuteActionFilterAsyncCore>d__5.MoveNext()\r\n--- End of stack trace from previous location where exception was thrown ---\r\n   at System.Runtime.CompilerServices.TaskAwaiter.ThrowForNonSuccess(Task task)\r\n   at System.Runtime.CompilerServices.TaskAwaiter.HandleNonSuccessAndDebuggerNotification(Task task)\r\n   at System.Web.Http.Filters.ActionFilterAttribute.<CallOnActionExecutedAsync>d__6.MoveNext()\r\n--- End of stack trace from previous location where exception was thrown ---\r\n   at System.Web.Http.Filters.ActionFilterAttribute.<CallOnActionExecutedAsync>d__6.MoveNext()\r\n--- End of stack trace from previous location where exception was thrown ---\r\n   at System.Runtime.CompilerServices.TaskAwaiter.ThrowForNonSuccess(Task task)\r\n   at System.Runtime.CompilerServices.TaskAwaiter.HandleNonSuccessAndDebuggerNotification(Task task)\r\n   at System.Web.Http.Filters.ActionFilterAttribute.<ExecuteActionFilterAsyncCore>d__5.MoveNext()\r\n--- End of stack trace from previous location where exception was thrown ---\r\n   at System.Runtime.CompilerServices.TaskAwaiter.ThrowForNonSuccess(Task task)\r\n   at System.Runtime.CompilerServices.TaskAwaiter.HandleNonSuccessAndDebuggerNotification(Task task)\r\n   at System.Web.Http.Filters.ActionFilterAttribute.<CallOnActionExecutedAsync>d__6.MoveNext()\r\n--- End of stack trace from previous location where exception was thrown ---\r\n   at System.Web.Http.Filters.ActionFilterAttribute.<CallOnActionExecutedAsync>d__6.MoveNext()\r\n--- End of stack trace from previous location where exception was thrown ---\r\n   at System.Runtime.CompilerServices.TaskAwaiter.ThrowForNonSuccess(Task task)\r\n   at System.Runtime.CompilerServices.TaskAwaiter.HandleNonSuccessAndDebuggerNotification(Task task)\r\n   at System.Web.Http.Filters.ActionFilterAttribute.<ExecuteActionFilterAsyncCore>d__5.MoveNext()\r\n--- End of stack trace from previous location where exception was thrown ---\r\n   at System.Runtime.CompilerServices.TaskAwaiter.ThrowForNonSuccess(Task task)\r\n   at System.Runtime.CompilerServices.TaskAwaiter.HandleNonSuccessAndDebuggerNotification(Task task)\r\n   at System.Web.Http.Filters.ActionFilterAttribute.<CallOnActionExecutedAsync>d__6.MoveNext()\r\n--- End of stack trace from previous location where exception was thrown ---\r\n   at System.Web.Http.Filters.ActionFilterAttribute.<CallOnActionExecutedAsync>d__6.MoveNext()\r\n--- End of stack trace from previous location where exception was thrown ---\r\n   at System.Runtime.CompilerServices.TaskAwaiter.ThrowForNonSuccess(Task task)\r\n   at System.Runtime.CompilerServices.TaskAwaiter.HandleNonSuccessAndDebuggerNotification(Task task)\r\n   at System.Web.Http.Filters.ActionFilterAttribute.<ExecuteActionFilterAsyncCore>d__5.MoveNext()\r\n--- End of stack trace from previous location where exception was thrown ---\r\n   at System.Runtime.CompilerServices.TaskAwaiter.ThrowForNonSuccess(Task task)\r\n   at System.Runtime.CompilerServices.TaskAwaiter.HandleNonSuccessAndDebuggerNotification(Task task)\r\n   at System.Web.Http.Filters.ActionFilterAttribute.<CallOnActionExecutedAsync>d__6.MoveNext()\r\n--- End of stack trace from previous location where exception was thrown ---\r\n   at System.Web.Http.Filters.ActionFilterAttribute.<CallOnActionExecutedAsync>d__6.MoveNext()\r\n--- End of stack trace from previous location where exception was thrown ---\r\n   at System.Runtime.CompilerServices.TaskAwaiter.ThrowForNonSuccess(Task task)\r\n   at System.Runtime.CompilerServices.TaskAwaiter.HandleNonSuccessAndDebuggerNotification(Task task)\r\n   at System.Web.Http.Filters.ActionFilterAttribute.<ExecuteActionFilterAsyncCore>d__5.MoveNext()\r\n--- End of stack trace from previous location where exception was thrown ---\r\n   at System.Runtime.CompilerServices.TaskAwaiter.ThrowForNonSuccess(Task task)\r\n   at System.Runtime.CompilerServices.TaskAwaiter.HandleNonSuccessAndDebuggerNotification(Task task)\r\n   at System.Web.Http.Filters.ActionFilterAttribute.<CallOnActionExecutedAsync>d__6.MoveNext()\r\n--- End of stack trace from previous location where exception was thrown ---\r\n   at System.Web.Http.Filters.ActionFilterAttribute.<CallOnActionExecutedAsync>d__6.MoveNext()\r\n--- End of stack trace from previous location where exception was thrown ---\r\n   at System.Runtime.CompilerServices.TaskAwaiter.ThrowForNonSuccess(Task task)\r\n   at System.Runtime.CompilerServices.TaskAwaiter.HandleNonSuccessAndDebuggerNotification(Task task)\r\n   at System.Web.Http.Filters.ActionFilterAttribute.<ExecuteActionFilterAsyncCore>d__5.MoveNext()\r\n--- End of stack trace from previous location where exception was thrown ---\r\n   at System.Runtime.CompilerServices.TaskAwaiter.ThrowForNonSuccess(Task task)\r\n   at System.Runtime.CompilerServices.TaskAwaiter.HandleNonSuccessAndDebuggerNotification(Task task)\r\n   at System.Web.Http.Controllers.ActionFilterResult.<ExecuteAsync>d__5.MoveNext()\r\n--- End of stack trace from previous location where exception was thrown ---\r\n   at System.Runtime.CompilerServices.TaskAwaiter.ThrowForNonSuccess(Task task)\r\n   at System.Runtime.CompilerServices.TaskAwaiter.HandleNonSuccessAndDebuggerNotification(Task task)\r\n   at System.Web.Http.Filters.AuthorizationFilterAttribute.<ExecuteAuthorizationFilterAsyncCore>d__3.MoveNext()\r\n--- End of stack trace from previous location where exception was thrown ---\r\n   at System.Runtime.CompilerServices.TaskAwaiter.ThrowForNonSuccess(Task task)\r\n   at System.Runtime.CompilerServices.TaskAwaiter.HandleNonSuccessAndDebuggerNotification(Task task)\r\n   at System.Web.Http.Filters.AuthorizationFilterAttribute.<ExecuteAuthorizationFilterAsyncCore>d__3.MoveNext()\r\n--- End of stack trace from previous location where exception was thrown ---\r\n   at System.Runtime.CompilerServices.TaskAwaiter.ThrowForNonSuccess(Task task)\r\n   at System.Runtime.CompilerServices.TaskAwaiter.HandleNonSuccessAndDebuggerNotification(Task task)\r\n   at System.Web.Http.Filters.AuthorizationFilterAttribute.<ExecuteAuthorizationFilterAsyncCore>d__3.MoveNext()\r\n--- End of stack trace from previous location where exception was thrown ---\r\n   at System.Runtime.CompilerServices.TaskAwaiter.ThrowForNonSuccess(Task task)\r\n   at System.Runtime.CompilerServices.TaskAwaiter.HandleNonSuccessAndDebuggerNotification(Task task)\r\n   at System.Web.Http.Filters.AuthorizationFilterAttribute.<ExecuteAuthorizationFilterAsyncCore>d__3.MoveNext()\r\n--- End of stack trace from previous location where exception was thrown ---\r\n   at System.Runtime.CompilerServices.TaskAwaiter.ThrowForNonSuccess(Task task)\r\n   at System.Runtime.CompilerServices.TaskAwaiter.HandleNonSuccessAndDebuggerNotification(Task task)\r\n   at System.Web.Http.Controllers.ExceptionFilterResult.<ExecuteAsync>d__6.MoveNext()\r\n--- End of stack trace from previous location where exception was thrown ---\r\n   at System.Web.Http.Controllers.ExceptionFilterResult.<ExecuteAsync>d__6.MoveNext()\r\n--- End of stack trace from previous location where exception was thrown ---\r\n   at System.Runtime.CompilerServices.TaskAwaiter.ThrowForNonSuccess(Task task)\r\n   at System.Runtime.CompilerServices.TaskAwaiter.HandleNonSuccessAndDebuggerNotification(Task task)\r\n   at System.Web.Http.Dispatcher.HttpControllerDispatcher.<SendAsync>d__15.MoveNext()","RequestUrl":"http://localhost:58464/umbraco/backoffice/UmbracoApi/Content/GetById?id=1148","SourceContext":"Umbraco.Web.Editors.ContentController","ProcessId":48900,"ProcessName":"iisexpress","ThreadId":16,"AppDomainId":2,"AppDomainAppId":"LMW3SVC2ROOT","MachineName":"CJ","Log4NetLevel":"ERROR","HttpRequestNumber":12,"HttpRequestId":"fc989f22-73be-41de-9b98-878f4873b709"}
